{
"meta":{"test_sets":[],"test_metrics":[],"learn_metrics":[{"best_value":"Min","name":"Logloss"}],"launch_mode":"Train","parameters":"","iteration_count":1000,"learn_sets":["learn"],"name":"experiment"},
"iterations":[
{"learn":[0.6459290451],"iteration":0,"passed_time":1.411689485,"remaining_time":1410.277796},
{"learn":[0.6098161438],"iteration":1,"passed_time":2.509177507,"remaining_time":1252.079576},
{"learn":[0.5817194078],"iteration":2,"passed_time":3.375556904,"remaining_time":1121.810078},
{"learn":[0.5609996904],"iteration":3,"passed_time":4.336011502,"remaining_time":1079.666864},
{"learn":[0.5446263012],"iteration":4,"passed_time":5.536590498,"remaining_time":1101.781509},
{"learn":[0.5324310588],"iteration":5,"passed_time":6.434529133,"remaining_time":1065.986993},
{"learn":[0.5226167033],"iteration":6,"passed_time":7.258216123,"remaining_time":1029.629801},
{"learn":[0.5139341712],"iteration":7,"passed_time":8.281317345,"remaining_time":1026.883351},
{"learn":[0.5070167408],"iteration":8,"passed_time":9.340249749,"remaining_time":1028.465278},
{"learn":[0.5020616694],"iteration":9,"passed_time":10.28027727,"remaining_time":1017.74745},
{"learn":[0.4974691085],"iteration":10,"passed_time":11.18468781,"remaining_time":1005.605113},
{"learn":[0.49326144],"iteration":11,"passed_time":12.02391206,"remaining_time":989.9687594},
{"learn":[0.4898663583],"iteration":12,"passed_time":13.16820442,"remaining_time":999.7705967},
{"learn":[0.4868991109],"iteration":13,"passed_time":14.43527228,"remaining_time":1016.655605},
{"learn":[0.4842466591],"iteration":14,"passed_time":15.43483527,"remaining_time":1013.554183},
{"learn":[0.4807556471],"iteration":15,"passed_time":16.44522004,"remaining_time":1011.381033},
{"learn":[0.47873831],"iteration":16,"passed_time":17.52927642,"remaining_time":1013.604631},
{"learn":[0.4767049825],"iteration":17,"passed_time":18.60240677,"remaining_time":1014.864636},
{"learn":[0.4745381796],"iteration":18,"passed_time":19.66493975,"remaining_time":1015.331889},
{"learn":[0.4728927255],"iteration":19,"passed_time":20.73379845,"remaining_time":1015.956124},
{"learn":[0.4715212579],"iteration":20,"passed_time":21.72219896,"remaining_time":1012.668228},
{"learn":[0.4700809648],"iteration":21,"passed_time":22.73270508,"remaining_time":1010.572071},
{"learn":[0.4688800008],"iteration":22,"passed_time":23.62932338,"remaining_time":1003.732563},
{"learn":[0.4674369806],"iteration":23,"passed_time":24.55079474,"remaining_time":998.3989862},
{"learn":[0.4665194372],"iteration":24,"passed_time":25.51756943,"remaining_time":995.1852078},
{"learn":[0.4646518068],"iteration":25,"passed_time":26.55617344,"remaining_time":994.8351129},
{"learn":[0.4635604255],"iteration":26,"passed_time":27.51325378,"remaining_time":991.4961454},
{"learn":[0.4623768135],"iteration":27,"passed_time":28.45518742,"remaining_time":987.801506},
{"learn":[0.4615417943],"iteration":28,"passed_time":29.44679907,"remaining_time":985.9600654},
{"learn":[0.4605621384],"iteration":29,"passed_time":30.37797048,"remaining_time":982.2210454},
{"learn":[0.4596183556],"iteration":30,"passed_time":31.36933573,"remaining_time":980.54472},
{"learn":[0.458713684],"iteration":31,"passed_time":32.34073564,"remaining_time":978.3072531},
{"learn":[0.4574698968],"iteration":32,"passed_time":33.32617372,"remaining_time":976.5578784},
{"learn":[0.4565741262],"iteration":33,"passed_time":34.45148331,"remaining_time":978.8274375},
{"learn":[0.4557485184],"iteration":34,"passed_time":35.54716249,"remaining_time":980.0860514},
{"learn":[0.4547510426],"iteration":35,"passed_time":36.42225161,"remaining_time":975.3069598},
{"learn":[0.4541805125],"iteration":36,"passed_time":37.38355602,"remaining_time":972.9828229},
{"learn":[0.4534139185],"iteration":37,"passed_time":38.37902094,"remaining_time":971.5952143},
{"learn":[0.4525859129],"iteration":38,"passed_time":39.45368575,"remaining_time":972.1792821},
{"learn":[0.4519187455],"iteration":39,"passed_time":40.34724346,"remaining_time":968.333843},
{"learn":[0.4509794638],"iteration":40,"passed_time":41.44521036,"remaining_time":969.4135788},
{"learn":[0.4499335284],"iteration":41,"passed_time":42.52335621,"remaining_time":969.9375059},
{"learn":[0.4490443481],"iteration":42,"passed_time":43.72019,"remaining_time":973.0284145},
{"learn":[0.4483988527],"iteration":43,"passed_time":44.69283942,"remaining_time":971.0535109},
{"learn":[0.4476485509],"iteration":44,"passed_time":45.82599326,"remaining_time":972.5294124},
{"learn":[0.447119201],"iteration":45,"passed_time":46.84212566,"remaining_time":971.4649539},
{"learn":[0.4464540262],"iteration":46,"passed_time":47.93697779,"remaining_time":971.9987198},
{"learn":[0.4458797718],"iteration":47,"passed_time":48.84549383,"remaining_time":968.768961},
{"learn":[0.4453967982],"iteration":48,"passed_time":49.90369822,"remaining_time":968.5391227},
{"learn":[0.4448635926],"iteration":49,"passed_time":50.78705768,"remaining_time":964.954096},
{"learn":[0.4441727771],"iteration":50,"passed_time":51.9491266,"remaining_time":966.6611989},
{"learn":[0.4437450078],"iteration":51,"passed_time":52.90467215,"remaining_time":964.4928691},
{"learn":[0.4433403996],"iteration":52,"passed_time":53.88295496,"remaining_time":962.7765726},
{"learn":[0.4426122842],"iteration":53,"passed_time":54.86757978,"remaining_time":961.1987124},
{"learn":[0.4422853772],"iteration":54,"passed_time":55.75085593,"remaining_time":957.90107},
{"learn":[0.441841678],"iteration":55,"passed_time":56.88286081,"remaining_time":958.8825107},
{"learn":[0.4413817105],"iteration":56,"passed_time":57.83573534,"remaining_time":956.8262881},
{"learn":[0.4409800831],"iteration":57,"passed_time":58.8093286,"remaining_time":955.1446128},
{"learn":[0.4401628051],"iteration":58,"passed_time":60.15929475,"remaining_time":959.4897689},
{"learn":[0.4398303429],"iteration":59,"passed_time":61.18126638,"remaining_time":958.5065066},
{"learn":[0.4392190167],"iteration":60,"passed_time":62.35568899,"remaining_time":959.8687207},
{"learn":[0.4387826629],"iteration":61,"passed_time":63.34948179,"remaining_time":958.4163536},
{"learn":[0.4384854746],"iteration":62,"passed_time":64.17202802,"remaining_time":954.4315914},
{"learn":[0.4381073004],"iteration":63,"passed_time":65.1565425,"remaining_time":952.9144341},
{"learn":[0.4377399937],"iteration":64,"passed_time":66.04509764,"remaining_time":950.0333276},
{"learn":[0.4372865802],"iteration":65,"passed_time":67.1055529,"remaining_time":949.6452486},
{"learn":[0.4369106083],"iteration":66,"passed_time":68.327463,"remaining_time":951.4854175},
{"learn":[0.4362031343],"iteration":67,"passed_time":69.58588371,"remaining_time":953.7359355},
{"learn":[0.43577396],"iteration":68,"passed_time":70.6635576,"remaining_time":953.4459729},
{"learn":[0.4354822947],"iteration":69,"passed_time":71.41574853,"remaining_time":948.8092305},
{"learn":[0.4352417984],"iteration":70,"passed_time":72.39461505,"remaining_time":947.2478504},
{"learn":[0.4350045503],"iteration":71,"passed_time":73.28014758,"remaining_time":944.49968},
{"learn":[0.4343102997],"iteration":72,"passed_time":74.48372662,"remaining_time":945.8412955},
{"learn":[0.4340003554],"iteration":73,"passed_time":75.55867933,"remaining_time":945.5045549},
{"learn":[0.4337624687],"iteration":74,"passed_time":76.44155125,"remaining_time":942.7791321},
{"learn":[0.4334959847],"iteration":75,"passed_time":77.36050601,"remaining_time":940.5408889},
{"learn":[0.4332658408],"iteration":76,"passed_time":78.33744237,"remaining_time":939.0319391},
{"learn":[0.433000018],"iteration":77,"passed_time":79.39395673,"remaining_time":938.4772834},
{"learn":[0.432672209],"iteration":78,"passed_time":80.30686581,"remaining_time":936.2357393},
{"learn":[0.4323670633],"iteration":79,"passed_time":81.34470991,"remaining_time":935.4641639},
{"learn":[0.4321096836],"iteration":80,"passed_time":82.54551927,"remaining_time":936.5349656},
{"learn":[0.4318887059],"iteration":81,"passed_time":83.42679513,"remaining_time":933.9731455},
{"learn":[0.4316286998],"iteration":82,"passed_time":84.42540142,"remaining_time":932.7481097},
{"learn":[0.431292793],"iteration":83,"passed_time":85.44422904,"remaining_time":931.7489738},
{"learn":[0.4309555582],"iteration":84,"passed_time":86.28573821,"remaining_time":928.8405937},
{"learn":[0.4307232495],"iteration":85,"passed_time":87.21905979,"remaining_time":926.956054},
{"learn":[0.4303472366],"iteration":86,"passed_time":88.22150585,"remaining_time":925.8187912},
{"learn":[0.4300805114],"iteration":87,"passed_time":89.37529764,"remaining_time":926.2530846},
{"learn":[0.4295280621],"iteration":88,"passed_time":90.60314395,"remaining_time":927.4097094},
{"learn":[0.4293412639],"iteration":89,"passed_time":91.51591957,"remaining_time":925.3276312},
{"learn":[0.4290311986],"iteration":90,"passed_time":92.54585841,"remaining_time":924.4415966},
{"learn":[0.4287913145],"iteration":91,"passed_time":93.54840377,"remaining_time":923.282072},
{"learn":[0.4285628521],"iteration":92,"passed_time":94.6108055,"remaining_time":922.7096838},
{"learn":[0.4283379537],"iteration":93,"passed_time":95.65917481,"remaining_time":921.991621},
{"learn":[0.4280848816],"iteration":94,"passed_time":96.59379526,"remaining_time":920.1829969},
{"learn":[0.4278293597],"iteration":95,"passed_time":97.70466676,"remaining_time":920.0522787},
{"learn":[0.4274626961],"iteration":96,"passed_time":98.79623905,"remaining_time":919.7216893},
{"learn":[0.4272977701],"iteration":97,"passed_time":99.937226,"remaining_time":919.8303863},
{"learn":[0.4271090114],"iteration":98,"passed_time":100.9241109,"remaining_time":918.5113527},
{"learn":[0.4268834979],"iteration":99,"passed_time":101.7807453,"remaining_time":916.0267078},
{"learn":[0.4263764371],"iteration":100,"passed_time":102.9823387,"remaining_time":916.644777},
{"learn":[0.4261921782],"iteration":101,"passed_time":104.1543757,"remaining_time":916.9669549},
{"learn":[0.4259761394],"iteration":102,"passed_time":105.1500186,"remaining_time":915.723948},
{"learn":[0.4257637844],"iteration":103,"passed_time":106.1629892,"remaining_time":914.634984},
{"learn":[0.4255831912],"iteration":104,"passed_time":107.0449226,"remaining_time":912.4305306},
{"learn":[0.425423161],"iteration":105,"passed_time":108.0156055,"remaining_time":910.9995406},
{"learn":[0.4252192997],"iteration":106,"passed_time":108.9839633,"remaining_time":909.55775},
{"learn":[0.4248319949],"iteration":107,"passed_time":110.0040544,"remaining_time":908.5520049},
{"learn":[0.4246015332],"iteration":108,"passed_time":110.8855258,"remaining_time":906.4128758},
{"learn":[0.4243556199],"iteration":109,"passed_time":112.1202724,"remaining_time":907.1549313},
{"learn":[0.4241311725],"iteration":110,"passed_time":113.1127506,"remaining_time":905.9210389},
{"learn":[0.4239203554],"iteration":111,"passed_time":114.0591125,"remaining_time":904.3258201},
{"learn":[0.4234606043],"iteration":112,"passed_time":115.2387431,"remaining_time":904.5731426},
{"learn":[0.4232818078],"iteration":113,"passed_time":116.0583089,"remaining_time":901.9970322},
{"learn":[0.4230565977],"iteration":114,"passed_time":117.1333545,"remaining_time":901.4175539},
{"learn":[0.4228434585],"iteration":115,"passed_time":118.0482306,"remaining_time":899.6089301},
{"learn":[0.4226680004],"iteration":116,"passed_time":119.012112,"remaining_time":898.1854262},
{"learn":[0.4224567524],"iteration":117,"passed_time":119.9997296,"remaining_time":896.9471314},
{"learn":[0.4222581864],"iteration":118,"passed_time":120.9205805,"remaining_time":895.2187518},
{"learn":[0.422047174],"iteration":119,"passed_time":121.9658748,"remaining_time":894.4164154},
{"learn":[0.4218233266],"iteration":120,"passed_time":122.9933031,"remaining_time":893.4802766},
{"learn":[0.4216017706],"iteration":121,"passed_time":123.9890325,"remaining_time":892.3145124},
{"learn":[0.4214118269],"iteration":122,"passed_time":124.9770987,"remaining_time":891.0968743},
{"learn":[0.4209789951],"iteration":123,"passed_time":125.9973931,"remaining_time":890.1106161},
{"learn":[0.4207762826],"iteration":124,"passed_time":126.8155071,"remaining_time":887.7085499},
{"learn":[0.4204060963],"iteration":125,"passed_time":127.9327234,"remaining_time":887.4063511},
{"learn":[0.4201522403],"iteration":126,"passed_time":129.0914103,"remaining_time":887.3763871},
{"learn":[0.4199975118],"iteration":127,"passed_time":130.0004651,"remaining_time":885.6281688},
{"learn":[0.4197359208],"iteration":128,"passed_time":131.0798951,"remaining_time":885.0433227},
{"learn":[0.4195159472],"iteration":129,"passed_time":132.3283641,"remaining_time":885.5821287},
{"learn":[0.4193418644],"iteration":130,"passed_time":133.2842107,"remaining_time":884.1525123},
{"learn":[0.419116276],"iteration":131,"passed_time":134.3122401,"remaining_time":883.20473},
{"learn":[0.4189738604],"iteration":132,"passed_time":135.1470743,"remaining_time":880.9963417},
{"learn":[0.4187267381],"iteration":133,"passed_time":136.1394703,"remaining_time":879.8267262},
{"learn":[0.4183562715],"iteration":134,"passed_time":137.5394206,"remaining_time":881.2711025},
{"learn":[0.4181772751],"iteration":135,"passed_time":138.5600582,"remaining_time":880.2638992},
{"learn":[0.418006018],"iteration":136,"passed_time":139.5804667,"remaining_time":879.2550564},
{"learn":[0.4178609886],"iteration":137,"passed_time":140.5291715,"remaining_time":877.7981582},
{"learn":[0.417681494],"iteration":138,"passed_time":141.5603927,"remaining_time":876.8596985},
{"learn":[0.4175255121],"iteration":139,"passed_time":142.4235666,"remaining_time":874.8876234},
{"learn":[0.4173871056],"iteration":140,"passed_time":143.3638446,"remaining_time":873.4010109},
{"learn":[0.4171950605],"iteration":141,"passed_time":144.3949323,"remaining_time":872.4707883},
{"learn":[0.4170686778],"iteration":142,"passed_time":145.2899065,"remaining_time":870.7234257},
{"learn":[0.4168357124],"iteration":143,"passed_time":146.3813567,"remaining_time":870.1558423},
{"learn":[0.4166772873],"iteration":144,"passed_time":147.2260394,"remaining_time":868.1259562},
{"learn":[0.4164726262],"iteration":145,"passed_time":148.1033711,"remaining_time":866.3032805},
{"learn":[0.4163294496],"iteration":146,"passed_time":149.084552,"remaining_time":865.096074},
{"learn":[0.4162078879],"iteration":147,"passed_time":149.9821277,"remaining_time":863.4106269},
{"learn":[0.4159992034],"iteration":148,"passed_time":151.069427,"remaining_time":862.8193449},
{"learn":[0.4158386407],"iteration":149,"passed_time":152.1370225,"remaining_time":862.1097941},
{"learn":[0.4157219256],"iteration":150,"passed_time":152.9758596,"remaining_time":860.1093036},
{"learn":[0.4155286],"iteration":151,"passed_time":154.1119135,"remaining_time":859.7822542},
{"learn":[0.4153726951],"iteration":152,"passed_time":155.1525327,"remaining_time":858.9163087},
{"learn":[0.4151691998],"iteration":153,"passed_time":156.3630683,"remaining_time":858.9815309},
{"learn":[0.4150705371],"iteration":154,"passed_time":157.2515248,"remaining_time":857.2744417},
{"learn":[0.4149433088],"iteration":155,"passed_time":158.1093169,"remaining_time":855.4119453},
{"learn":[0.4148326734],"iteration":156,"passed_time":159.1226053,"remaining_time":854.3971735},
{"learn":[0.4146802017],"iteration":157,"passed_time":160.1171278,"remaining_time":853.282415},
{"learn":[0.414540833],"iteration":158,"passed_time":160.9548239,"remaining_time":851.3396659},
{"learn":[0.4143550122],"iteration":159,"passed_time":162.09924,"remaining_time":851.02101},
{"learn":[0.4142067262],"iteration":160,"passed_time":162.9790302,"remaining_time":849.3130831},
{"learn":[0.4140611525],"iteration":161,"passed_time":163.8680127,"remaining_time":847.6629297},
{"learn":[0.4139690297],"iteration":162,"passed_time":164.65609,"remaining_time":845.5039713},
{"learn":[0.4137953505],"iteration":163,"passed_time":165.9147071,"remaining_time":845.7603362},
{"learn":[0.4135923474],"iteration":164,"passed_time":167.0082732,"remaining_time":845.1630795},
{"learn":[0.4133767422],"iteration":165,"passed_time":168.1859266,"remaining_time":844.9823061},
{"learn":[0.4132584071],"iteration":166,"passed_time":169.0999585,"remaining_time":843.4746435},
{"learn":[0.4131054594],"iteration":167,"passed_time":170.0893674,"remaining_time":842.3473433},
{"learn":[0.4129797356],"iteration":168,"passed_time":171.1025864,"remaining_time":841.3387532},
{"learn":[0.4128599841],"iteration":169,"passed_time":172.0621953,"remaining_time":840.0683655},
{"learn":[0.4125956451],"iteration":170,"passed_time":173.4619953,"remaining_time":840.9356381},
{"learn":[0.4123657245],"iteration":171,"passed_time":174.7326122,"remaining_time":841.1546681},
{"learn":[0.4122359996],"iteration":172,"passed_time":175.9170899,"remaining_time":840.9447015},
{"learn":[0.412112267],"iteration":173,"passed_time":176.7410143,"remaining_time":839.0119415},
{"learn":[0.4120089403],"iteration":174,"passed_time":177.6028623,"remaining_time":837.2706366},
{"learn":[0.4118503562],"iteration":175,"passed_time":178.5957453,"remaining_time":836.1528075},
{"learn":[0.4117089234],"iteration":176,"passed_time":179.5836654,"remaining_time":835.0133144},
{"learn":[0.4116222897],"iteration":177,"passed_time":180.4920124,"remaining_time":833.5080575},
{"learn":[0.4115320753],"iteration":178,"passed_time":181.3725597,"remaining_time":831.8819636},
{"learn":[0.4113592284],"iteration":179,"passed_time":182.5581953,"remaining_time":831.6540008},
{"learn":[0.4111274616],"iteration":180,"passed_time":183.7821488,"remaining_time":831.5888391},
{"learn":[0.4110318467],"iteration":181,"passed_time":184.7771132,"remaining_time":830.4817504},
{"learn":[0.4108545841],"iteration":182,"passed_time":185.9713259,"remaining_time":830.2654274},
{"learn":[0.4107234656],"iteration":183,"passed_time":187.1498401,"remaining_time":829.968856},
{"learn":[0.4106081988],"iteration":184,"passed_time":188.0276233,"remaining_time":828.337908},
{"learn":[0.410474769],"iteration":185,"passed_time":189.1359434,"remaining_time":827.7239672},
{"learn":[0.4103469108],"iteration":186,"passed_time":190.1694689,"remaining_time":826.7795628},
{"learn":[0.4102321783],"iteration":187,"passed_time":191.0720863,"remaining_time":825.2687982},
{"learn":[0.4101371657],"iteration":188,"passed_time":191.9034468,"remaining_time":823.4587057},
{"learn":[0.4099771991],"iteration":189,"passed_time":193.070744,"remaining_time":823.0910665},
{"learn":[0.4097678641],"iteration":190,"passed_time":194.4480235,"remaining_time":823.6044557},
{"learn":[0.4096148718],"iteration":191,"passed_time":195.7318291,"remaining_time":823.7047809},
{"learn":[0.4095379699],"iteration":192,"passed_time":196.49302,"remaining_time":821.6055293},
{"learn":[0.4094024221],"iteration":193,"passed_time":197.6199516,"remaining_time":821.0395928},
{"learn":[0.4093133071],"iteration":194,"passed_time":198.6705388,"remaining_time":820.1527372},
{"learn":[0.4092147925],"iteration":195,"passed_time":199.5149139,"remaining_time":818.4183203},
{"learn":[0.4091089142],"iteration":196,"passed_time":200.5398685,"remaining_time":817.4290073},
{"learn":[0.4090173177],"iteration":197,"passed_time":201.5132307,"remaining_time":816.2303588},
{"learn":[0.4088975659],"iteration":198,"passed_time":202.7144913,"remaining_time":815.951294},
{"learn":[0.4087807872],"iteration":199,"passed_time":203.9477651,"remaining_time":815.7910603},
{"learn":[0.4086427839],"iteration":200,"passed_time":205.0776619,"remaining_time":815.2092131},
{"learn":[0.4085050918],"iteration":201,"passed_time":206.1760254,"remaining_time":814.4973677},
{"learn":[0.4083692589],"iteration":202,"passed_time":207.2619975,"remaining_time":813.733064},
{"learn":[0.4082524703],"iteration":203,"passed_time":208.4079312,"remaining_time":813.1995745},
{"learn":[0.4081073155],"iteration":204,"passed_time":209.2963223,"remaining_time":811.6613473},
{"learn":[0.4079903047],"iteration":205,"passed_time":210.3155899,"remaining_time":810.6338758},
{"learn":[0.4078693532],"iteration":206,"passed_time":211.2949496,"remaining_time":809.453599},
{"learn":[0.4077404704],"iteration":207,"passed_time":212.6553772,"remaining_time":809.7262439},
{"learn":[0.4076322049],"iteration":208,"passed_time":213.7456881,"remaining_time":808.9609536},
{"learn":[0.4075063426],"iteration":209,"passed_time":214.8781953,"remaining_time":808.351306},
{"learn":[0.4074166723],"iteration":210,"passed_time":215.8102772,"remaining_time":806.9872452},
{"learn":[0.4073304312],"iteration":211,"passed_time":216.8105377,"remaining_time":805.8806778},
{"learn":[0.4071260121],"iteration":212,"passed_time":218.2839275,"remaining_time":806.5232438},
{"learn":[0.4070587533],"iteration":213,"passed_time":219.0139326,"remaining_time":804.4156591},
{"learn":[0.4069215114],"iteration":214,"passed_time":220.1146857,"remaining_time":803.6745499},
{"learn":[0.4068204769],"iteration":215,"passed_time":221.0111477,"remaining_time":802.1886103},
{"learn":[0.4067551497],"iteration":216,"passed_time":221.7406049,"remaining_time":800.1055007},
{"learn":[0.4066009458],"iteration":217,"passed_time":222.7899506,"remaining_time":799.1823},
{"learn":[0.4065109323],"iteration":218,"passed_time":223.5622118,"remaining_time":797.2698057},
{"learn":[0.4064329568],"iteration":219,"passed_time":224.5769029,"remaining_time":796.2272013},
{"learn":[0.406347682],"iteration":220,"passed_time":225.3537645,"remaining_time":794.3465274},
{"learn":[0.4062725268],"iteration":221,"passed_time":226.4027528,"remaining_time":793.4294672},
{"learn":[0.4061961445],"iteration":222,"passed_time":227.2320823,"remaining_time":791.7458653},
{"learn":[0.4061195547],"iteration":223,"passed_time":228.0770687,"remaining_time":790.1241308},
{"learn":[0.4060274508],"iteration":224,"passed_time":228.8694032,"remaining_time":788.3279444},
{"learn":[0.4059446913],"iteration":225,"passed_time":229.7391775,"remaining_time":786.8058558},
{"learn":[0.405852697],"iteration":226,"passed_time":230.6229164,"remaining_time":785.3370677},
{"learn":[0.4057710679],"iteration":227,"passed_time":231.5126037,"remaining_time":783.8935529},
{"learn":[0.4056889328],"iteration":228,"passed_time":232.4699329,"remaining_time":782.6826125},
{"learn":[0.4056154354],"iteration":229,"passed_time":233.4523962,"remaining_time":781.558022},
{"learn":[0.4055547928],"iteration":230,"passed_time":234.3180175,"remaining_time":780.0456945},
{"learn":[0.4054791821],"iteration":231,"passed_time":235.1247755,"remaining_time":778.3440843},
{"learn":[0.405396481],"iteration":232,"passed_time":236.3636342,"remaining_time":778.0725642},
{"learn":[0.4051851978],"iteration":233,"passed_time":237.4761794,"remaining_time":777.3792881},
{"learn":[0.4050566843],"iteration":234,"passed_time":238.4474123,"remaining_time":776.2224272},
{"learn":[0.4049845506],"iteration":235,"passed_time":239.2823795,"remaining_time":774.6260083},
{"learn":[0.4048903381],"iteration":236,"passed_time":240.2555948,"remaining_time":773.4810921},
{"learn":[0.4048235498],"iteration":237,"passed_time":241.0016201,"remaining_time":771.6102289},
{"learn":[0.4047385176],"iteration":238,"passed_time":242.2838207,"remaining_time":771.4560148},
{"learn":[0.4046674762],"iteration":239,"passed_time":243.2666069,"remaining_time":770.3442552},
{"learn":[0.4045699576],"iteration":240,"passed_time":244.0781664,"remaining_time":768.6943082},
{"learn":[0.4044459958],"iteration":241,"passed_time":245.1442787,"remaining_time":767.8486084},
{"learn":[0.4043540354],"iteration":242,"passed_time":246.0829558,"remaining_time":766.6041052},
{"learn":[0.4042788608],"iteration":243,"passed_time":246.9106023,"remaining_time":765.0180958},
{"learn":[0.4041962772],"iteration":244,"passed_time":247.8364663,"remaining_time":763.740947},
{"learn":[0.4040853635],"iteration":245,"passed_time":248.833974,"remaining_time":762.6862456},
{"learn":[0.4040111016],"iteration":246,"passed_time":249.7706908,"remaining_time":761.4466808},
{"learn":[0.4038901187],"iteration":247,"passed_time":250.9737706,"remaining_time":761.01724},
{"learn":[0.4037826874],"iteration":248,"passed_time":251.9699869,"remaining_time":759.9576714},
{"learn":[0.4037101924],"iteration":249,"passed_time":252.8222917,"remaining_time":758.4668751},
{"learn":[0.4035718282],"iteration":250,"passed_time":253.756659,"remaining_time":757.2260461},
{"learn":[0.4034630564],"iteration":251,"passed_time":254.7578753,"remaining_time":756.1860742},
{"learn":[0.4033869998],"iteration":252,"passed_time":255.7026277,"remaining_time":754.9796952},
{"learn":[0.403313124],"iteration":253,"passed_time":256.4997433,"remaining_time":753.3417658},
{"learn":[0.4031415922],"iteration":254,"passed_time":257.6946296,"remaining_time":752.8725454},
{"learn":[0.4030806522],"iteration":255,"passed_time":258.6490617,"remaining_time":751.6988355},
{"learn":[0.4029300861],"iteration":256,"passed_time":259.7221877,"remaining_time":750.8699824},
{"learn":[0.4028599475],"iteration":257,"passed_time":260.6638002,"remaining_time":749.6610069},
{"learn":[0.4027641858],"iteration":258,"passed_time":261.6345053,"remaining_time":748.5373298},
{"learn":[0.4026580438],"iteration":259,"passed_time":262.6910505,"remaining_time":747.6591437},
{"learn":[0.4025881142],"iteration":260,"passed_time":263.6650427,"remaining_time":746.5458489},
{"learn":[0.4025183345],"iteration":261,"passed_time":264.6337164,"remaining_time":745.4186364},
{"learn":[0.4024527857],"iteration":262,"passed_time":265.4184145,"remaining_time":743.7770778},
{"learn":[0.4023793616],"iteration":263,"passed_time":266.6979725,"remaining_time":743.5216203},
{"learn":[0.4023256668],"iteration":264,"passed_time":267.4656684,"remaining_time":741.8387408},
{"learn":[0.40225658],"iteration":265,"passed_time":268.2504032,"remaining_time":740.2097592},
{"learn":[0.4021850053],"iteration":266,"passed_time":269.2602994,"remaining_time":739.2052414},
{"learn":[0.4021178722],"iteration":267,"passed_time":270.119979,"remaining_time":737.7903903},
{"learn":[0.4020217455],"iteration":268,"passed_time":271.2553259,"remaining_time":737.1287852},
{"learn":[0.4019560302],"iteration":269,"passed_time":272.1894338,"remaining_time":735.9195802},
{"learn":[0.4018832345],"iteration":270,"passed_time":273.1676527,"remaining_time":734.8310658},
{"learn":[0.4018160727],"iteration":271,"passed_time":274.217868,"remaining_time":733.9360585},
{"learn":[0.4017528355],"iteration":272,"passed_time":275.0412082,"remaining_time":732.4357449},
{"learn":[0.4016760231],"iteration":273,"passed_time":275.943663,"remaining_time":731.1499976},
{"learn":[0.4016037883],"iteration":274,"passed_time":276.8024001,"remaining_time":729.7517821},
{"learn":[0.4015279825],"iteration":275,"passed_time":277.9950251,"remaining_time":729.2333267},
{"learn":[0.4014376812],"iteration":276,"passed_time":278.8107037,"remaining_time":727.7261327},
{"learn":[0.4013283629],"iteration":277,"passed_time":279.7691692,"remaining_time":726.5947489},
{"learn":[0.4011876472],"iteration":278,"passed_time":281.0157512,"remaining_time":726.2091635},
{"learn":[0.4010826257],"iteration":279,"passed_time":281.9080648,"remaining_time":724.9064523},
{"learn":[0.4009881573],"iteration":280,"passed_time":282.9760315,"remaining_time":724.0561089},
{"learn":[0.4008897961],"iteration":281,"passed_time":284.005709,"remaining_time":723.1067343},
{"learn":[0.4008167497],"iteration":282,"passed_time":284.8860392,"remaining_time":721.7784102},
{"learn":[0.4007194385],"iteration":283,"passed_time":285.8829511,"remaining_time":720.7471583},
{"learn":[0.4006503576],"iteration":284,"passed_time":286.7662291,"remaining_time":719.4310661},
{"learn":[0.4005685818],"iteration":285,"passed_time":287.7810142,"remaining_time":718.4463082},
{"learn":[0.4004989261],"iteration":286,"passed_time":288.6915356,"remaining_time":717.2023166},
{"learn":[0.4004177213],"iteration":287,"passed_time":289.720552,"remaining_time":716.2535869},
{"learn":[0.4003204361],"iteration":288,"passed_time":290.6930443,"remaining_time":715.1652404},
{"learn":[0.4002714899],"iteration":289,"passed_time":291.5080734,"remaining_time":713.6921797},
{"learn":[0.4001703912],"iteration":290,"passed_time":292.4793125,"remaining_time":712.6042356},
{"learn":[0.4000732455],"iteration":291,"passed_time":293.4788027,"remaining_time":711.5855902},
{"learn":[0.3999928535],"iteration":292,"passed_time":294.4731973,"remaining_time":710.5547798},
{"learn":[0.3999142272],"iteration":293,"passed_time":295.4079148,"remaining_time":709.380911},
{"learn":[0.3997996695],"iteration":294,"passed_time":296.593611,"remaining_time":708.8084601},
{"learn":[0.3996955754],"iteration":295,"passed_time":297.5741788,"remaining_time":707.7439928},
{"learn":[0.3996298599],"iteration":296,"passed_time":298.4331571,"remaining_time":706.3922877},
{"learn":[0.3995419931],"iteration":297,"passed_time":299.7278671,"remaining_time":706.0703445},
{"learn":[0.3994695533],"iteration":298,"passed_time":300.7352156,"remaining_time":705.068181},
{"learn":[0.3994044039],"iteration":299,"passed_time":301.5827266,"remaining_time":703.6930288},
{"learn":[0.399331114],"iteration":300,"passed_time":302.5337987,"remaining_time":702.561878},
{"learn":[0.3992571633],"iteration":301,"passed_time":303.5587282,"remaining_time":701.6026234},
{"learn":[0.3991688356],"iteration":302,"passed_time":304.375418,"remaining_time":700.1639154},
{"learn":[0.3991003073],"iteration":303,"passed_time":305.3080205,"remaining_time":698.9946786},
{"learn":[0.399021563],"iteration":304,"passed_time":306.3486899,"remaining_time":698.0732441},
{"learn":[0.398929802],"iteration":305,"passed_time":307.6045753,"remaining_time":697.6391349},
{"learn":[0.3988744495],"iteration":306,"passed_time":308.3042135,"remaining_time":695.944039},
{"learn":[0.398803834],"iteration":307,"passed_time":309.2989417,"remaining_time":694.9184015},
{"learn":[0.3987351036],"iteration":308,"passed_time":310.036625,"remaining_time":693.3181484},
{"learn":[0.3986571697],"iteration":309,"passed_time":311.1373482,"remaining_time":692.5315169},
{"learn":[0.3985551624],"iteration":310,"passed_time":312.3683316,"remaining_time":692.0314485},
{"learn":[0.398484878],"iteration":311,"passed_time":313.4083069,"remaining_time":691.1054974},
{"learn":[0.3984208704],"iteration":312,"passed_time":314.2760346,"remaining_time":689.8007532},
{"learn":[0.3983467347],"iteration":313,"passed_time":315.1653917,"remaining_time":688.5460468},
{"learn":[0.3982712442],"iteration":314,"passed_time":316.159761,"remaining_time":687.5220199},
{"learn":[0.3981921449],"iteration":315,"passed_time":317.3515715,"remaining_time":686.9255535},
{"learn":[0.398125975],"iteration":316,"passed_time":318.3854972,"remaining_time":685.9851564},
{"learn":[0.3980569567],"iteration":317,"passed_time":319.2970724,"remaining_time":684.7817717},
{"learn":[0.3979917278],"iteration":318,"passed_time":320.0336535,"remaining_time":683.2066396},
{"learn":[0.3979397775],"iteration":319,"passed_time":320.7320914,"remaining_time":681.5556943},
{"learn":[0.3978530166],"iteration":320,"passed_time":321.6499615,"remaining_time":680.3748407},
{"learn":[0.3977640902],"iteration":321,"passed_time":322.4522671,"remaining_time":678.9522891},
{"learn":[0.3976989725],"iteration":322,"passed_time":323.3141298,"remaining_time":677.6584082},
{"learn":[0.3976332202],"iteration":323,"passed_time":324.2343986,"remaining_time":676.4890539},
{"learn":[0.3975669469],"iteration":324,"passed_time":325.0792359,"remaining_time":675.1645668},
{"learn":[0.3974605229],"iteration":325,"passed_time":326.1300901,"remaining_time":674.2689593},
{"learn":[0.3973938682],"iteration":326,"passed_time":327.2780526,"remaining_time":673.5722611},
{"learn":[0.397316962],"iteration":327,"passed_time":328.4572405,"remaining_time":672.9367855},
{"learn":[0.3972497453],"iteration":328,"passed_time":329.3428021,"remaining_time":671.6991496},
{"learn":[0.3971743306],"iteration":329,"passed_time":330.2953066,"remaining_time":670.5995618},
{"learn":[0.3970779248],"iteration":330,"passed_time":331.4116507,"remaining_time":669.8320071},
{"learn":[0.3969908687],"iteration":331,"passed_time":332.3493709,"remaining_time":668.7029511},
{"learn":[0.3969240467],"iteration":332,"passed_time":333.3218295,"remaining_time":667.6446254},
{"learn":[0.3968353425],"iteration":333,"passed_time":334.366607,"remaining_time":666.7310187},
{"learn":[0.396750942],"iteration":334,"passed_time":335.2074432,"remaining_time":665.4117903},
{"learn":[0.396693453],"iteration":335,"passed_time":336.0879995,"remaining_time":664.1739038},
{"learn":[0.3966222326],"iteration":336,"passed_time":337.1026081,"remaining_time":663.2018669},
{"learn":[0.3965384484],"iteration":337,"passed_time":338.2152094,"remaining_time":662.4215048},
{"learn":[0.3964795619],"iteration":338,"passed_time":339.1554771,"remaining_time":661.3031574},
{"learn":[0.396418363],"iteration":339,"passed_time":339.8312663,"remaining_time":659.6724582},
{"learn":[0.3963436986],"iteration":340,"passed_time":340.7629007,"remaining_time":658.5417934},
{"learn":[0.3962509193],"iteration":341,"passed_time":341.9507914,"remaining_time":657.9053237},
{"learn":[0.3961835159],"iteration":342,"passed_time":342.7760069,"remaining_time":656.5709521},
{"learn":[0.3961216236],"iteration":343,"passed_time":343.6091935,"remaining_time":655.254741},
{"learn":[0.3960538538],"iteration":344,"passed_time":344.671076,"remaining_time":654.3755211},
{"learn":[0.3959949357],"iteration":345,"passed_time":345.5259034,"remaining_time":653.1038752},
{"learn":[0.3959200779],"iteration":346,"passed_time":346.5327876,"remaining_time":652.1207789},
{"learn":[0.3958434741],"iteration":347,"passed_time":347.6389364,"remaining_time":651.3235245},
{"learn":[0.395742952],"iteration":348,"passed_time":348.5519272,"remaining_time":650.1641965},
{"learn":[0.3956621107],"iteration":349,"passed_time":349.6946021,"remaining_time":649.4328326},
{"learn":[0.3955928754],"iteration":350,"passed_time":350.7816923,"remaining_time":648.5963485},
{"learn":[0.3955233759],"iteration":351,"passed_time":351.8614736,"remaining_time":647.7449855},
{"learn":[0.3954596787],"iteration":352,"passed_time":352.6925801,"remaining_time":646.436542},
{"learn":[0.3953874052],"iteration":353,"passed_time":353.4813091,"remaining_time":645.0534623},
{"learn":[0.3953154146],"iteration":354,"passed_time":354.6151945,"remaining_time":644.3008463},
{"learn":[0.3952545269],"iteration":355,"passed_time":355.4331981,"remaining_time":642.9746618},
{"learn":[0.3951880628],"iteration":356,"passed_time":356.5748703,"remaining_time":642.2342903},
{"learn":[0.3951319341],"iteration":357,"passed_time":357.2245555,"remaining_time":640.6093984},
{"learn":[0.3950807917],"iteration":358,"passed_time":357.9438397,"remaining_time":639.1142096},
{"learn":[0.3950181249],"iteration":359,"passed_time":358.6937641,"remaining_time":637.6778029},
{"learn":[0.3949501054],"iteration":360,"passed_time":359.4754045,"remaining_time":636.3013392},
{"learn":[0.3948835614],"iteration":361,"passed_time":360.4051916,"remaining_time":635.1892604},
{"learn":[0.3948160583],"iteration":362,"passed_time":361.1988367,"remaining_time":633.8392809},
{"learn":[0.3947627952],"iteration":363,"passed_time":361.8941481,"remaining_time":632.3205446},
{"learn":[0.3946895584],"iteration":364,"passed_time":363.0334047,"remaining_time":631.5786629},
{"learn":[0.3946234374],"iteration":365,"passed_time":364.1771228,"remaining_time":630.8423384},
{"learn":[0.3945547067],"iteration":366,"passed_time":365.2332993,"remaining_time":629.9528023},
{"learn":[0.3944909457],"iteration":367,"passed_time":366.1650576,"remaining_time":628.8486858},
{"learn":[0.3944259624],"iteration":368,"passed_time":367.1375387,"remaining_time":627.8151407},
{"learn":[0.3943347081],"iteration":369,"passed_time":368.3262306,"remaining_time":627.1500684},
{"learn":[0.3942633743],"iteration":370,"passed_time":369.4904452,"remaining_time":626.440674},
{"learn":[0.3942065623],"iteration":371,"passed_time":370.249757,"remaining_time":625.0452887},
{"learn":[0.3941435454],"iteration":372,"passed_time":370.9886583,"remaining_time":623.6190047},
{"learn":[0.3940768199],"iteration":373,"passed_time":371.816575,"remaining_time":622.3453902},
{"learn":[0.3940149425],"iteration":374,"passed_time":372.7626497,"remaining_time":621.2710828},
{"learn":[0.393953174],"iteration":375,"passed_time":373.7420562,"remaining_time":620.2527742},
{"learn":[0.3939006144],"iteration":376,"passed_time":374.6152369,"remaining_time":619.0591316},
{"learn":[0.3938398222],"iteration":377,"passed_time":375.4490273,"remaining_time":617.8023677},
{"learn":[0.3937821328],"iteration":378,"passed_time":376.3628882,"remaining_time":616.6790331},
{"learn":[0.3937179185],"iteration":379,"passed_time":377.2985199,"remaining_time":615.592322},
{"learn":[0.3936573323],"iteration":380,"passed_time":378.1296634,"remaining_time":614.3366447},
{"learn":[0.3935905682],"iteration":381,"passed_time":379.0416551,"remaining_time":613.2139865},
{"learn":[0.3935158744],"iteration":382,"passed_time":379.8643645,"remaining_time":611.9485976},
{"learn":[0.3934607506],"iteration":383,"passed_time":380.9004611,"remaining_time":611.0278229},
{"learn":[0.3933984473],"iteration":384,"passed_time":381.6326589,"remaining_time":609.6210006},
{"learn":[0.3932872985],"iteration":385,"passed_time":382.6438567,"remaining_time":608.6614715},
{"learn":[0.3931546116],"iteration":386,"passed_time":383.8453192,"remaining_time":608.0030508},
{"learn":[0.3930615709],"iteration":387,"passed_time":384.7531424,"remaining_time":606.878668},
{"learn":[0.3930012816],"iteration":388,"passed_time":385.6617491,"remaining_time":605.756629},
{"learn":[0.3929359059],"iteration":389,"passed_time":386.8130398,"remaining_time":605.0152673},
{"learn":[0.3928618017],"iteration":390,"passed_time":387.599697,"remaining_time":603.7038759},
{"learn":[0.3927921819],"iteration":391,"passed_time":388.4749021,"remaining_time":602.5325013},
{"learn":[0.3927199928],"iteration":392,"passed_time":389.7118128,"remaining_time":601.9212986},
{"learn":[0.3926568856],"iteration":393,"passed_time":390.549092,"remaining_time":600.6922582},
{"learn":[0.3926095116],"iteration":394,"passed_time":391.2932924,"remaining_time":599.3226377},
{"learn":[0.392537738],"iteration":395,"passed_time":392.2601439,"remaining_time":598.295775},
{"learn":[0.392480996],"iteration":396,"passed_time":393.1158522,"remaining_time":597.1004002},
{"learn":[0.3923993761],"iteration":397,"passed_time":394.142958,"remaining_time":596.1659817},
{"learn":[0.3922967872],"iteration":398,"passed_time":395.118069,"remaining_time":595.1527807},
{"learn":[0.3922278148],"iteration":399,"passed_time":395.8971974,"remaining_time":593.8457961},
{"learn":[0.3921785222],"iteration":400,"passed_time":396.6531565,"remaining_time":592.5068347},
{"learn":[0.3921058015],"iteration":401,"passed_time":397.6536143,"remaining_time":591.534481},
{"learn":[0.3920322683],"iteration":402,"passed_time":398.8625602,"remaining_time":590.8708398},
{"learn":[0.3919774728],"iteration":403,"passed_time":399.735903,"remaining_time":589.7094014},
{"learn":[0.3919059683],"iteration":404,"passed_time":400.5476228,"remaining_time":588.4588532},
{"learn":[0.3918467157],"iteration":405,"passed_time":401.3042111,"remaining_time":587.1298065},
{"learn":[0.3917804497],"iteration":406,"passed_time":402.08716,"remaining_time":585.8419801},
{"learn":[0.3917210444],"iteration":407,"passed_time":403.0267672,"remaining_time":584.7839367},
{"learn":[0.3916468953],"iteration":408,"passed_time":403.91937,"remaining_time":583.6585517},
{"learn":[0.3915774431],"iteration":409,"passed_time":404.8535003,"remaining_time":582.5940614},
{"learn":[0.3915017154],"iteration":410,"passed_time":405.6684255,"remaining_time":581.3593738},
{"learn":[0.3914316479],"iteration":411,"passed_time":406.6819631,"remaining_time":580.4101804},
{"learn":[0.3913414753],"iteration":412,"passed_time":407.8072148,"remaining_time":579.6194554},
{"learn":[0.3912845554],"iteration":413,"passed_time":408.7050483,"remaining_time":578.5052132},
{"learn":[0.3912255043],"iteration":414,"passed_time":409.6059191,"remaining_time":577.3962956},
{"learn":[0.3911186639],"iteration":415,"passed_time":410.5637784,"remaining_time":576.3683812},
{"learn":[0.3910477823],"iteration":416,"passed_time":411.4925115,"remaining_time":575.300082},
{"learn":[0.3909781763],"iteration":417,"passed_time":412.2815787,"remaining_time":574.0379876},
{"learn":[0.3909059774],"iteration":418,"passed_time":413.2687442,"remaining_time":573.052841},
{"learn":[0.3908389976],"iteration":419,"passed_time":414.2142093,"remaining_time":572.0100986},
{"learn":[0.3907505405],"iteration":420,"passed_time":415.2109676,"remaining_time":571.0383616},
{"learn":[0.3906974585],"iteration":421,"passed_time":416.034852,"remaining_time":569.8297261},
{"learn":[0.3906128221],"iteration":422,"passed_time":417.2898406,"remaining_time":569.2109646},
{"learn":[0.3905454613],"iteration":423,"passed_time":418.1920471,"remaining_time":568.1099507},
{"learn":[0.3904746687],"iteration":424,"passed_time":419.1327191,"remaining_time":567.061914},
{"learn":[0.3904114489],"iteration":425,"passed_time":419.9909343,"remaining_time":565.9032777},
{"learn":[0.3903709538],"iteration":426,"passed_time":420.667326,"remaining_time":564.5020558},
{"learn":[0.3903080712],"iteration":427,"passed_time":421.4684681,"remaining_time":563.2709434},
{"learn":[0.3902540404],"iteration":428,"passed_time":422.3060931,"remaining_time":562.0903943},
{"learn":[0.3901962599],"iteration":429,"passed_time":423.1259391,"remaining_time":560.8878727},
{"learn":[0.3901409904],"iteration":430,"passed_time":423.9492003,"remaining_time":559.6916357},
{"learn":[0.3900845128],"iteration":431,"passed_time":424.6852672,"remaining_time":558.3824809},
{"learn":[0.3900284039],"iteration":432,"passed_time":425.6980074,"remaining_time":557.4382683},
{"learn":[0.389953766],"iteration":433,"passed_time":426.5503344,"remaining_time":556.2845375},
{"learn":[0.3898940328],"iteration":434,"passed_time":427.3719554,"remaining_time":555.0923099},
{"learn":[0.3898235572],"iteration":435,"passed_time":428.2874778,"remaining_time":554.023251},
{"learn":[0.3897299246],"iteration":436,"passed_time":429.2060642,"remaining_time":552.9588425},
{"learn":[0.3896580223],"iteration":437,"passed_time":430.2617209,"remaining_time":552.0709752},
{"learn":[0.3895780287],"iteration":438,"passed_time":431.1973734,"remaining_time":551.0289896},
{"learn":[0.3895148438],"iteration":439,"passed_time":432.0474056,"remaining_time":549.8785163},
{"learn":[0.3894297671],"iteration":440,"passed_time":433.2297419,"remaining_time":549.1506252},
{"learn":[0.3893739885],"iteration":441,"passed_time":434.1116421,"remaining_time":548.0413944},
{"learn":[0.3893212583],"iteration":442,"passed_time":434.8129819,"remaining_time":546.7061646},
{"learn":[0.3892448316],"iteration":443,"passed_time":435.7796888,"remaining_time":545.7060968},
{"learn":[0.3891822606],"iteration":444,"passed_time":436.6444038,"remaining_time":544.5789755},
{"learn":[0.3891095223],"iteration":445,"passed_time":437.7847195,"remaining_time":543.7953691},
{"learn":[0.3890491394],"iteration":446,"passed_time":438.5413764,"remaining_time":542.5355283},
{"learn":[0.3889850916],"iteration":447,"passed_time":439.5726359,"remaining_time":541.6162835},
{"learn":[0.3889217148],"iteration":448,"passed_time":440.5014043,"remaining_time":540.5707657},
{"learn":[0.3888552834],"iteration":449,"passed_time":441.3268858,"remaining_time":539.3995271},
{"learn":[0.3887901955],"iteration":450,"passed_time":442.0858655,"remaining_time":538.1488695},
{"learn":[0.3887286353],"iteration":451,"passed_time":443.1563643,"remaining_time":537.27807},
{"learn":[0.3886605003],"iteration":452,"passed_time":443.9895779,"remaining_time":536.1198655},
{"learn":[0.388597059],"iteration":453,"passed_time":444.9657295,"remaining_time":535.1349962},
{"learn":[0.3885311645],"iteration":454,"passed_time":445.7858095,"remaining_time":533.9632224},
{"learn":[0.3884388278],"iteration":455,"passed_time":446.922719,"remaining_time":533.170963},
{"learn":[0.388370813],"iteration":456,"passed_time":448.117034,"remaining_time":532.4454036},
{"learn":[0.3883207622],"iteration":457,"passed_time":448.8492169,"remaining_time":531.1709074},
{"learn":[0.3882547259],"iteration":458,"passed_time":449.8718843,"remaining_time":530.2411534},
{"learn":[0.388195235],"iteration":459,"passed_time":450.8082132,"remaining_time":529.2096416},
{"learn":[0.3881411887],"iteration":460,"passed_time":451.5276007,"remaining_time":527.9248954},
{"learn":[0.3880812243],"iteration":461,"passed_time":452.5335073,"remaining_time":526.9762488},
{"learn":[0.3880183523],"iteration":462,"passed_time":453.3428768,"remaining_time":525.7994057},
{"learn":[0.3878957866],"iteration":463,"passed_time":454.400017,"remaining_time":524.9103645},
{"learn":[0.3878327962],"iteration":464,"passed_time":455.3827857,"remaining_time":523.935033},
{"learn":[0.387762349],"iteration":465,"passed_time":456.4835975,"remaining_time":523.094938},
{"learn":[0.3877035612],"iteration":466,"passed_time":457.2926998,"remaining_time":521.9207901},
{"learn":[0.387623799],"iteration":467,"passed_time":458.3014976,"remaining_time":520.9752066},
{"learn":[0.3875611238],"iteration":468,"passed_time":459.1848821,"remaining_time":519.8873612},
{"learn":[0.3874980377],"iteration":469,"passed_time":460.0788676,"remaining_time":518.81234},
{"learn":[0.3874314269],"iteration":470,"passed_time":460.9147199,"remaining_time":517.6727959},
{"learn":[0.3873532584],"iteration":471,"passed_time":462.098531,"remaining_time":516.9237805},
{"learn":[0.3872976771],"iteration":472,"passed_time":463.0017373,"remaining_time":515.8602865},
{"learn":[0.3872372383],"iteration":473,"passed_time":463.8987749,"remaining_time":514.7906237},
{"learn":[0.3871872846],"iteration":474,"passed_time":464.8379741,"remaining_time":513.7682871},
{"learn":[0.3871392078],"iteration":475,"passed_time":465.6004385,"remaining_time":512.5517433},
{"learn":[0.3870861488],"iteration":476,"passed_time":466.574561,"remaining_time":511.5691727},
{"learn":[0.387033574],"iteration":477,"passed_time":467.4764221,"remaining_time":510.5077245},
{"learn":[0.3869674656],"iteration":478,"passed_time":468.4472128,"remaining_time":509.5219162},
{"learn":[0.3869146464],"iteration":479,"passed_time":469.3320274,"remaining_time":508.4430296},
{"learn":[0.3868524717],"iteration":480,"passed_time":470.1862574,"remaining_time":507.3319492},
{"learn":[0.3868016655],"iteration":481,"passed_time":471.0264381,"remaining_time":506.206836},
{"learn":[0.3867312848],"iteration":482,"passed_time":472.0009632,"remaining_time":505.2267039},
{"learn":[0.3866677683],"iteration":483,"passed_time":472.9275614,"remaining_time":504.1954993},
{"learn":[0.3865989356],"iteration":484,"passed_time":473.7617478,"remaining_time":503.0665982},
{"learn":[0.3865358749],"iteration":485,"passed_time":474.5306195,"remaining_time":501.8698321},
{"learn":[0.386490704],"iteration":486,"passed_time":475.3891291,"remaining_time":500.7692469},
{"learn":[0.3864184886],"iteration":487,"passed_time":476.4135595,"remaining_time":499.8437346},
{"learn":[0.3863603083],"iteration":488,"passed_time":477.3534619,"remaining_time":498.8294868},
{"learn":[0.3862930408],"iteration":489,"passed_time":478.1888343,"remaining_time":497.706746},
{"learn":[0.3862056865],"iteration":490,"passed_time":479.1785821,"remaining_time":496.7452104},
{"learn":[0.3861401205],"iteration":491,"passed_time":480.1251282,"remaining_time":495.7389535},
{"learn":[0.3860828972],"iteration":492,"passed_time":480.9323007,"remaining_time":494.5896074},
{"learn":[0.3860162199],"iteration":493,"passed_time":481.9276939,"remaining_time":493.6344395},
{"learn":[0.3859479264],"iteration":494,"passed_time":482.7918498,"remaining_time":492.5452205},
{"learn":[0.3858887343],"iteration":495,"passed_time":483.7391845,"remaining_time":491.5414295},
{"learn":[0.3858353733],"iteration":496,"passed_time":484.7261529,"remaining_time":490.5779777},
{"learn":[0.385782357],"iteration":497,"passed_time":485.6690754,"remaining_time":489.5700318},
{"learn":[0.3857254797],"iteration":498,"passed_time":486.5013641,"remaining_time":488.4512694},
{"learn":[0.3856663115],"iteration":499,"passed_time":487.2850388,"remaining_time":487.2850388},
{"learn":[0.3855994037],"iteration":500,"passed_time":488.1031699,"remaining_time":486.1546542},
{"learn":[0.3855411975],"iteration":501,"passed_time":488.9309053,"remaining_time":485.0350415},
{"learn":[0.3854900301],"iteration":502,"passed_time":489.8385155,"remaining_time":483.9955113},
{"learn":[0.3854242369],"iteration":503,"passed_time":490.8049712,"remaining_time":483.0144161},
{"learn":[0.3853575269],"iteration":504,"passed_time":491.817385,"remaining_time":482.0784269},
{"learn":[0.3852889278],"iteration":505,"passed_time":492.6949093,"remaining_time":481.010445},
{"learn":[0.3852314086],"iteration":506,"passed_time":493.3985493,"remaining_time":479.7741318},
{"learn":[0.3851605664],"iteration":507,"passed_time":494.3723609,"remaining_time":478.8015779},
{"learn":[0.385098356],"iteration":508,"passed_time":495.2664716,"remaining_time":477.7521366},
{"learn":[0.3850361307],"iteration":509,"passed_time":496.345996,"remaining_time":476.8814472},
{"learn":[0.3849861492],"iteration":510,"passed_time":497.2144936,"remaining_time":475.8079987},
{"learn":[0.3849240601],"iteration":511,"passed_time":498.2370973,"remaining_time":474.8822334},
{"learn":[0.3848531617],"iteration":512,"passed_time":499.0149121,"remaining_time":473.7237079},
{"learn":[0.3847999323],"iteration":513,"passed_time":499.7816929,"remaining_time":472.556231},
{"learn":[0.3847352496],"iteration":514,"passed_time":500.5815475,"remaining_time":471.4214573},
{"learn":[0.3846740158],"iteration":515,"passed_time":501.4011826,"remaining_time":470.3065356},
{"learn":[0.384612499],"iteration":516,"passed_time":502.3003766,"remaining_time":469.267083},
{"learn":[0.3845476463],"iteration":517,"passed_time":503.2089899,"remaining_time":468.2369366},
{"learn":[0.3844802132],"iteration":518,"passed_time":504.1880367,"remaining_time":467.272535},
{"learn":[0.3844074981],"iteration":519,"passed_time":505.3325458,"remaining_time":466.4608115},
{"learn":[0.3843564802],"iteration":520,"passed_time":506.0179631,"remaining_time":465.2257281},
{"learn":[0.3842963534],"iteration":521,"passed_time":506.9430058,"remaining_time":464.2121778},
{"learn":[0.3842397827],"iteration":522,"passed_time":507.8464071,"remaining_time":463.1792279},
{"learn":[0.3841792466],"iteration":523,"passed_time":508.8081824,"remaining_time":462.1997993},
{"learn":[0.3841162122],"iteration":524,"passed_time":509.8444043,"remaining_time":461.2877944},
{"learn":[0.384041403],"iteration":525,"passed_time":511.0854222,"remaining_time":460.5598671},
{"learn":[0.3839768396],"iteration":526,"passed_time":512.1693142,"remaining_time":459.688967},
{"learn":[0.3839145615],"iteration":527,"passed_time":513.1677551,"remaining_time":458.7408719},
{"learn":[0.3838563908],"iteration":528,"passed_time":514.0609573,"remaining_time":457.6988864},
{"learn":[0.3837563364],"iteration":529,"passed_time":515.2226041,"remaining_time":456.8955168},
{"learn":[0.3836961625],"iteration":530,"passed_time":516.1199956,"remaining_time":455.8573972},
{"learn":[0.3836345902],"iteration":531,"passed_time":516.8925642,"remaining_time":454.7100001},
{"learn":[0.3835693249],"iteration":532,"passed_time":517.7572506,"remaining_time":453.6447205},
{"learn":[0.383504472],"iteration":533,"passed_time":518.8602357,"remaining_time":452.7881458},
{"learn":[0.3834423197],"iteration":534,"passed_time":519.9635318,"remaining_time":451.9309202},
{"learn":[0.3833769156],"iteration":535,"passed_time":521.0868554,"remaining_time":451.0901136},
{"learn":[0.3833142612],"iteration":536,"passed_time":522.0936565,"remaining_time":450.1477895},
{"learn":[0.3832670009],"iteration":537,"passed_time":522.9283004,"remaining_time":449.0573881},
{"learn":[0.3832154769],"iteration":538,"passed_time":523.6874608,"remaining_time":447.9033755},
{"learn":[0.3831611346],"iteration":539,"passed_time":524.4480959,"remaining_time":446.7520817},
{"learn":[0.3830973811],"iteration":540,"passed_time":525.2180272,"remaining_time":445.6101192},
{"learn":[0.3830402697],"iteration":541,"passed_time":526.272203,"remaining_time":444.7097213},
{"learn":[0.3829811519],"iteration":542,"passed_time":527.3428539,"remaining_time":443.8226229},
{"learn":[0.3829167115],"iteration":543,"passed_time":528.3491231,"remaining_time":442.8808826},
{"learn":[0.3828484814],"iteration":544,"passed_time":529.1784537,"remaining_time":441.7911861},
{"learn":[0.3827878233],"iteration":545,"passed_time":530.1777003,"remaining_time":440.8437288},
{"learn":[0.3827278595],"iteration":546,"passed_time":531.131178,"remaining_time":439.8581785},
{"learn":[0.3826763596],"iteration":547,"passed_time":531.9574872,"remaining_time":438.7678544},
{"learn":[0.3825960798],"iteration":548,"passed_time":532.9313367,"remaining_time":437.7996956},
{"learn":[0.3825338105],"iteration":549,"passed_time":533.7773131,"remaining_time":436.7268926},
{"learn":[0.3824676019],"iteration":550,"passed_time":534.7665662,"remaining_time":435.7716665},
{"learn":[0.3824143702],"iteration":551,"passed_time":535.7571846,"remaining_time":434.8174252},
{"learn":[0.3823662672],"iteration":552,"passed_time":536.5617279,"remaining_time":433.7126445},
{"learn":[0.3823180233],"iteration":553,"passed_time":537.3472162,"remaining_time":432.5936073},
{"learn":[0.3822603068],"iteration":554,"passed_time":538.3313285,"remaining_time":431.6350292},
{"learn":[0.3821898988],"iteration":555,"passed_time":539.5575695,"remaining_time":430.8697138},
{"learn":[0.3821226025],"iteration":556,"passed_time":540.4539762,"remaining_time":429.8404155},
{"learn":[0.3820617247],"iteration":557,"passed_time":541.4522645,"remaining_time":428.8922955},
{"learn":[0.382002432],"iteration":558,"passed_time":542.2660316,"remaining_time":427.7984256},
{"learn":[0.3819361715],"iteration":559,"passed_time":543.1958076,"remaining_time":426.7967059},
{"learn":[0.3818712767],"iteration":560,"passed_time":544.1992414,"remaining_time":425.8528823},
{"learn":[0.3818090733],"iteration":561,"passed_time":545.3450425,"remaining_time":425.0198018},
{"learn":[0.3817446268],"iteration":562,"passed_time":546.3387823,"remaining_time":424.0675806},
{"learn":[0.3816889835],"iteration":563,"passed_time":547.1378205,"remaining_time":422.9646981},
{"learn":[0.3816189944],"iteration":564,"passed_time":547.9748743,"remaining_time":421.8921599},
{"learn":[0.381539129],"iteration":565,"passed_time":549.1641521,"remaining_time":421.0905336},
{"learn":[0.3814786927],"iteration":566,"passed_time":550.049347,"remaining_time":420.0553214},
{"learn":[0.3814149969],"iteration":567,"passed_time":550.9452679,"remaining_time":419.0287953},
{"learn":[0.3813549597],"iteration":568,"passed_time":551.9586415,"remaining_time":418.091695},
{"learn":[0.3813038595],"iteration":569,"passed_time":552.9880953,"remaining_time":417.1664578},
{"learn":[0.3812456605],"iteration":570,"passed_time":553.7642775,"remaining_time":416.0505692},
{"learn":[0.3811987821],"iteration":571,"passed_time":554.6256848,"remaining_time":414.9996383},
{"learn":[0.3811394117],"iteration":572,"passed_time":555.6508534,"remaining_time":414.0714039},
{"learn":[0.3810943388],"iteration":573,"passed_time":556.511163,"remaining_time":413.0204799},
{"learn":[0.3810314124],"iteration":574,"passed_time":557.4589618,"remaining_time":412.0348848},
{"learn":[0.3809598985],"iteration":575,"passed_time":558.4471406,"remaining_time":411.0791452},
{"learn":[0.3808917705],"iteration":576,"passed_time":559.530061,"remaining_time":410.1927483},
{"learn":[0.3808327417],"iteration":577,"passed_time":560.4759099,"remaining_time":409.2055951},
{"learn":[0.3807644461],"iteration":578,"passed_time":561.3758603,"remaining_time":408.185211},
{"learn":[0.3806971995],"iteration":579,"passed_time":562.1689786,"remaining_time":407.0878811},
{"learn":[0.3806275968],"iteration":580,"passed_time":563.2463782,"remaining_time":406.1966136},
{"learn":[0.3805732804],"iteration":581,"passed_time":564.1951925,"remaining_time":405.2123548},
{"learn":[0.3805200217],"iteration":582,"passed_time":565.1502978,"remaining_time":404.2327173},
{"learn":[0.3804646692],"iteration":583,"passed_time":566.0731574,"remaining_time":403.2301943},
{"learn":[0.3804014737],"iteration":584,"passed_time":567.076689,"remaining_time":402.2851726},
{"learn":[0.3803376233],"iteration":585,"passed_time":567.9732211,"remaining_time":401.2643575},
{"learn":[0.3802783833],"iteration":586,"passed_time":569.0391489,"remaining_time":400.3631491},
{"learn":[0.3802146777],"iteration":587,"passed_time":570.04458,"remaining_time":399.4189914},
{"learn":[0.3801547601],"iteration":588,"passed_time":570.9861507,"remaining_time":398.4300644},
{"learn":[0.3800914939],"iteration":589,"passed_time":572.0625729,"remaining_time":397.5350083},
{"learn":[0.3800371096],"iteration":590,"passed_time":572.8641471,"remaining_time":396.4491306},
{"learn":[0.3799799639],"iteration":591,"passed_time":573.7873778,"remaining_time":395.4480577},
{"learn":[0.3799199008],"iteration":592,"passed_time":574.7149742,"remaining_time":394.4502436},
{"learn":[0.3798456352],"iteration":593,"passed_time":575.8043731,"remaining_time":393.5632584},
{"learn":[0.3797742035],"iteration":594,"passed_time":576.9965679,"remaining_time":392.745563},
{"learn":[0.3797177944],"iteration":595,"passed_time":577.8509503,"remaining_time":391.6976241},
{"learn":[0.3796409075],"iteration":596,"passed_time":578.8199828,"remaining_time":390.7277271},
{"learn":[0.3795765042],"iteration":597,"passed_time":579.9675458,"remaining_time":389.8778485},
{"learn":[0.3795235873],"iteration":598,"passed_time":580.982044,"remaining_time":388.9378959},
{"learn":[0.3794666855],"iteration":599,"passed_time":581.9266888,"remaining_time":387.9511258},
{"learn":[0.3794136126],"iteration":600,"passed_time":582.765669,"remaining_time":386.894346},
{"learn":[0.3793418873],"iteration":601,"passed_time":583.7432753,"remaining_time":385.9299395},
{"learn":[0.3792883484],"iteration":602,"passed_time":584.480948,"remaining_time":384.807523},
{"learn":[0.3792269631],"iteration":603,"passed_time":585.3765169,"remaining_time":383.7899018},
{"learn":[0.3791601571],"iteration":604,"passed_time":586.47806,"remaining_time":382.9071631},
{"learn":[0.3791079939],"iteration":605,"passed_time":587.4873491,"remaining_time":381.963722},
{"learn":[0.3790476598],"iteration":606,"passed_time":588.3073417,"remaining_time":380.8975046},
{"learn":[0.3789883371],"iteration":607,"passed_time":589.2436025,"remaining_time":379.9070595},
{"learn":[0.3789335301],"iteration":608,"passed_time":589.9416341,"remaining_time":378.7638406},
{"learn":[0.378869212],"iteration":609,"passed_time":591.0334291,"remaining_time":377.8738317},
{"learn":[0.3788059742],"iteration":610,"passed_time":592.3635147,"remaining_time":377.1348727},
{"learn":[0.3787445851],"iteration":611,"passed_time":594.1955122,"remaining_time":376.7121875},
{"learn":[0.378690235],"iteration":612,"passed_time":595.4554077,"remaining_time":375.923724},
{"learn":[0.3786358504],"iteration":613,"passed_time":596.8335246,"remaining_time":375.2080464},
{"learn":[0.3785798773],"iteration":614,"passed_time":597.9764985,"remaining_time":374.3430112},
{"learn":[0.3785162985],"iteration":615,"passed_time":599.3931523,"remaining_time":373.6476794},
{"learn":[0.3784585119],"iteration":616,"passed_time":600.6476285,"remaining_time":372.8493383},
{"learn":[0.3783988545],"iteration":617,"passed_time":601.848657,"remaining_time":372.0164838},
{"learn":[0.378338007],"iteration":618,"passed_time":603.1515656,"remaining_time":371.2451478},
{"learn":[0.3782755948],"iteration":619,"passed_time":604.7962481,"remaining_time":370.6815714},
{"learn":[0.3782052206],"iteration":620,"passed_time":606.5389759,"remaining_time":370.1743509},
{"learn":[0.378147067],"iteration":621,"passed_time":607.7955575,"remaining_time":369.3677182},
{"learn":[0.3780885849],"iteration":622,"passed_time":609.2821785,"remaining_time":368.6988464},
{"learn":[0.3780248017],"iteration":623,"passed_time":610.6292202,"remaining_time":367.9432481},
{"learn":[0.3779651505],"iteration":624,"passed_time":611.8279879,"remaining_time":367.0967927},
{"learn":[0.3778815892],"iteration":625,"passed_time":613.1580532,"remaining_time":366.3276548},
{"learn":[0.3777665476],"iteration":626,"passed_time":614.5495723,"remaining_time":365.5932862},
{"learn":[0.377709906],"iteration":627,"passed_time":616.0133019,"remaining_time":364.8995992},
{"learn":[0.3776502183],"iteration":628,"passed_time":617.3251495,"remaining_time":364.1138799},
{"learn":[0.3775808629],"iteration":629,"passed_time":618.7677441,"remaining_time":363.4032783},
{"learn":[0.3775200208],"iteration":630,"passed_time":619.9157575,"remaining_time":362.5180896},
{"learn":[0.3774799846],"iteration":631,"passed_time":620.9124006,"remaining_time":361.5439294},
{"learn":[0.3774303071],"iteration":632,"passed_time":622.1394771,"remaining_time":360.7032987},
{"learn":[0.3773807622],"iteration":633,"passed_time":623.4445816,"remaining_time":359.9064935},
{"learn":[0.3773188671],"iteration":634,"passed_time":624.9940092,"remaining_time":359.248525},
{"learn":[0.3772500865],"iteration":635,"passed_time":625.9637843,"remaining_time":358.2560023},
{"learn":[0.3771894012],"iteration":636,"passed_time":627.1787081,"remaining_time":357.4032512},
{"learn":[0.377135915],"iteration":637,"passed_time":628.2113813,"remaining_time":356.4459561},
{"learn":[0.3770477988],"iteration":638,"passed_time":630.0139633,"remaining_time":355.9233815},
{"learn":[0.3769956911],"iteration":639,"passed_time":631.3509632,"remaining_time":355.1349168},
{"learn":[0.3769376153],"iteration":640,"passed_time":632.625713,"remaining_time":354.3098767},
{"learn":[0.3768938932],"iteration":641,"passed_time":633.6953978,"remaining_time":353.3690848},
{"learn":[0.3768303285],"iteration":642,"passed_time":635.2307836,"remaining_time":352.6864537},
{"learn":[0.376772335],"iteration":643,"passed_time":636.4299349,"remaining_time":351.8153056},
{"learn":[0.3767084439],"iteration":644,"passed_time":637.5280317,"remaining_time":350.8875213},
{"learn":[0.3766423826],"iteration":645,"passed_time":638.8780908,"remaining_time":350.0972819},
{"learn":[0.3765870893],"iteration":646,"passed_time":640.0327775,"remaining_time":349.1987179},
{"learn":[0.3765264257],"iteration":647,"passed_time":641.2294655,"remaining_time":348.3221788},
{"learn":[0.3764725342],"iteration":648,"passed_time":642.7439289,"remaining_time":347.6165162},
{"learn":[0.3764205293],"iteration":649,"passed_time":644.0516279,"remaining_time":346.7970304},
{"learn":[0.3763609242],"iteration":650,"passed_time":645.5319466,"remaining_time":346.0685858},
{"learn":[0.3763212535],"iteration":651,"passed_time":646.6542828,"remaining_time":345.1467644},
{"learn":[0.3762637519],"iteration":652,"passed_time":647.7127081,"remaining_time":344.1903671},
{"learn":[0.3762068269],"iteration":653,"passed_time":648.7555186,"remaining_time":343.2253967},
{"learn":[0.3761245297],"iteration":654,"passed_time":650.0837255,"remaining_time":342.4105119},
{"learn":[0.3760668411],"iteration":655,"passed_time":651.0269725,"remaining_time":341.3921929},
{"learn":[0.3760024661],"iteration":656,"passed_time":652.2240716,"remaining_time":340.506631},
{"learn":[0.3759402032],"iteration":657,"passed_time":653.7040133,"remaining_time":339.7671315},
{"learn":[0.3758841987],"iteration":658,"passed_time":654.7550458,"remaining_time":338.8034455},
{"learn":[0.375833385],"iteration":659,"passed_time":655.6149506,"remaining_time":337.7410352},
{"learn":[0.375773843],"iteration":660,"passed_time":656.6468141,"remaining_time":336.7674281},
{"learn":[0.37571069],"iteration":661,"passed_time":658.2813326,"remaining_time":336.101345},
{"learn":[0.3756443042],"iteration":662,"passed_time":659.9816469,"remaining_time":335.4657843},
{"learn":[0.3755894748],"iteration":663,"passed_time":661.6012902,"remaining_time":334.786195},
{"learn":[0.3755214762],"iteration":664,"passed_time":662.8830109,"remaining_time":333.9335468},
{"learn":[0.3754758505],"iteration":665,"passed_time":663.7318783,"remaining_time":332.8625336},
{"learn":[0.375434686],"iteration":666,"passed_time":664.6289046,"remaining_time":331.8162297},
{"learn":[0.3753766063],"iteration":667,"passed_time":665.8211444,"remaining_time":330.9170957},
{"learn":[0.3753119535],"iteration":668,"passed_time":666.9974185,"remaining_time":330.0091861},
{"learn":[0.3752474944],"iteration":669,"passed_time":668.3673862,"remaining_time":329.1958768},
{"learn":[0.3751887635],"iteration":670,"passed_time":669.5418732,"remaining_time":328.2850615},
{"learn":[0.3751382851],"iteration":671,"passed_time":670.5239757,"remaining_time":327.2795596},
{"learn":[0.3750698648],"iteration":672,"passed_time":672.0400224,"remaining_time":326.5335622},
{"learn":[0.3750224941],"iteration":673,"passed_time":673.5850983,"remaining_time":325.7993205},
{"learn":[0.374942976],"iteration":674,"passed_time":676.0398289,"remaining_time":325.5006584},
{"learn":[0.3748845339],"iteration":675,"passed_time":677.1979523,"remaining_time":324.5741665},
{"learn":[0.3748150591],"iteration":676,"passed_time":678.8408213,"remaining_time":323.8782648},
{"learn":[0.3747498991],"iteration":677,"passed_time":680.2382101,"remaining_time":323.0629847},
{"learn":[0.3746950657],"iteration":678,"passed_time":681.3408383,"remaining_time":322.1066408},
{"learn":[0.3746457772],"iteration":679,"passed_time":682.593512,"remaining_time":321.2204762},
{"learn":[0.3745960115],"iteration":680,"passed_time":683.5644159,"remaining_time":320.2012462},
{"learn":[0.3745250315],"iteration":681,"passed_time":684.9782937,"remaining_time":319.3887059},
{"learn":[0.374476539],"iteration":682,"passed_time":686.3186443,"remaining_time":318.5402786},
{"learn":[0.3744190471],"iteration":683,"passed_time":688.0011878,"remaining_time":317.8485019},
{"learn":[0.3743434781],"iteration":684,"passed_time":689.7337614,"remaining_time":317.1768392},
{"learn":[0.3742875651],"iteration":685,"passed_time":691.278215,"remaining_time":316.415976},
{"learn":[0.3741870459],"iteration":686,"passed_time":693.1372665,"remaining_time":315.7961636},
{"learn":[0.3741283134],"iteration":687,"passed_time":694.7187278,"remaining_time":315.0468649},
{"learn":[0.3740718517],"iteration":688,"passed_time":695.9724004,"remaining_time":314.1471938},
{"learn":[0.3740109155],"iteration":689,"passed_time":697.3584328,"remaining_time":313.3059626},
{"learn":[0.3739588566],"iteration":690,"passed_time":698.6192778,"remaining_time":312.4071734},
{"learn":[0.3739015959],"iteration":691,"passed_time":699.7268377,"remaining_time":311.4391127},
{"learn":[0.3738405793],"iteration":692,"passed_time":701.1390296,"remaining_time":310.6056019},
{"learn":[0.3737673556],"iteration":693,"passed_time":703.0211775,"remaining_time":309.9776373},
{"learn":[0.3737190589],"iteration":694,"passed_time":704.0234313,"remaining_time":308.9599231},
{"learn":[0.373660096],"iteration":695,"passed_time":705.8216964,"remaining_time":308.2899364},
{"learn":[0.3735976264],"iteration":696,"passed_time":707.5614197,"remaining_time":307.5912628},
{"learn":[0.3735494745],"iteration":697,"passed_time":708.7685237,"remaining_time":306.6591607},
{"learn":[0.3735037612],"iteration":698,"passed_time":709.8565588,"remaining_time":305.6749989},
{"learn":[0.3734510921],"iteration":699,"passed_time":711.4635275,"remaining_time":304.9129403},
{"learn":[0.373394512],"iteration":700,"passed_time":712.8862976,"remaining_time":304.0699044},
{"learn":[0.3733328061],"iteration":701,"passed_time":714.4101243,"remaining_time":303.2681154},
{"learn":[0.3732728618],"iteration":702,"passed_time":716.2568989,"remaining_time":302.6007098},
{"learn":[0.3732132948],"iteration":703,"passed_time":717.712407,"remaining_time":301.7654439},
{"learn":[0.3731566262],"iteration":704,"passed_time":718.9002284,"remaining_time":300.8164076},
{"learn":[0.3730995701],"iteration":705,"passed_time":720.0015107,"remaining_time":299.8306574},
{"learn":[0.3730538791],"iteration":706,"passed_time":721.4318361,"remaining_time":298.9809448},
{"learn":[0.372998218],"iteration":707,"passed_time":722.4315567,"remaining_time":297.951998},
{"learn":[0.3729419642],"iteration":708,"passed_time":723.661643,"remaining_time":297.0176842},
{"learn":[0.3728943606],"iteration":709,"passed_time":724.7938412,"remaining_time":296.0425549},
{"learn":[0.3728434081],"iteration":710,"passed_time":726.437186,"remaining_time":295.2747493},
{"learn":[0.3727922279],"iteration":711,"passed_time":727.4824684,"remaining_time":294.2625715},
{"learn":[0.3727203724],"iteration":712,"passed_time":729.3106428,"remaining_time":293.5654341},
{"learn":[0.3726576089],"iteration":713,"passed_time":731.5099561,"remaining_time":293.0137919},
{"learn":[0.3726118809],"iteration":714,"passed_time":733.1338107,"remaining_time":292.2281623},
{"learn":[0.3725460315],"iteration":715,"passed_time":734.7598418,"remaining_time":291.4410546},
{"learn":[0.3724467373],"iteration":716,"passed_time":736.2140166,"remaining_time":290.583775},
{"learn":[0.3723913116],"iteration":717,"passed_time":737.2692579,"remaining_time":289.5681486},
{"learn":[0.3723382479],"iteration":718,"passed_time":738.3636637,"remaining_time":288.5677183},
{"learn":[0.3722858281],"iteration":719,"passed_time":739.477472,"remaining_time":287.5745724},
{"learn":[0.372228663],"iteration":720,"passed_time":740.7489837,"remaining_time":286.6421171},
{"learn":[0.3721722563],"iteration":721,"passed_time":742.7319458,"remaining_time":285.9826606},
{"learn":[0.3721209312],"iteration":722,"passed_time":743.8802613,"remaining_time":284.9997682},
{"learn":[0.3720606023],"iteration":723,"passed_time":745.1179688,"remaining_time":284.0504964},
{"learn":[0.3719940179],"iteration":724,"passed_time":746.0844184,"remaining_time":282.997538},
{"learn":[0.3719219906],"iteration":725,"passed_time":747.5847233,"remaining_time":282.1463005},
{"learn":[0.3718628556],"iteration":726,"passed_time":748.714535,"remaining_time":281.1541514},
{"learn":[0.3718041087],"iteration":727,"passed_time":750.5249924,"remaining_time":280.4159312},
{"learn":[0.3717477578],"iteration":728,"passed_time":751.7127202,"remaining_time":279.4432746},
{"learn":[0.3716860643],"iteration":729,"passed_time":753.4623923,"remaining_time":278.6778711},
{"learn":[0.371623306],"iteration":730,"passed_time":755.5698156,"remaining_time":278.0414233},
{"learn":[0.3715628717],"iteration":731,"passed_time":757.171861,"remaining_time":277.2159273},
{"learn":[0.3714953315],"iteration":732,"passed_time":758.5448137,"remaining_time":276.3048639},
{"learn":[0.3714367831],"iteration":733,"passed_time":759.9724277,"remaining_time":275.4123512},
{"learn":[0.3713736441],"iteration":734,"passed_time":761.1475288,"remaining_time":274.4273403},
{"learn":[0.3713347799],"iteration":735,"passed_time":761.907749,"remaining_time":273.2929969},
{"learn":[0.3712742914],"iteration":736,"passed_time":762.8997015,"remaining_time":272.242363},
{"learn":[0.371207101],"iteration":737,"passed_time":764.138321,"remaining_time":271.2794581},
{"learn":[0.3711511936],"iteration":738,"passed_time":765.5749191,"remaining_time":270.3857292},
{"learn":[0.3711088987],"iteration":739,"passed_time":766.6779545,"remaining_time":269.3733354},
{"learn":[0.3710669523],"iteration":740,"passed_time":767.8117923,"remaining_time":268.3714632},
{"learn":[0.3710134134],"iteration":741,"passed_time":769.3481463,"remaining_time":267.5091937},
{"learn":[0.3709468094],"iteration":742,"passed_time":771.4842595,"remaining_time":266.8525635},
{"learn":[0.370897094],"iteration":743,"passed_time":773.0156988,"remaining_time":265.9838964},
{"learn":[0.3708408428],"iteration":744,"passed_time":774.2247614,"remaining_time":265.0031063},
{"learn":[0.3707906848],"iteration":745,"passed_time":775.1972766,"remaining_time":263.9411639},
{"learn":[0.3707482516],"iteration":746,"passed_time":775.9888142,"remaining_time":262.818166},
{"learn":[0.3706834675],"iteration":747,"passed_time":777.0669427,"remaining_time":261.7926064},
{"learn":[0.3706239231],"iteration":748,"passed_time":778.1641606,"remaining_time":260.7733035},
{"learn":[0.3705608507],"iteration":749,"passed_time":779.624244,"remaining_time":259.874748},
{"learn":[0.3705104295],"iteration":750,"passed_time":780.7424834,"remaining_time":258.861356},
{"learn":[0.3704647223],"iteration":751,"passed_time":781.9831066,"remaining_time":257.8880458},
{"learn":[0.3703958683],"iteration":752,"passed_time":783.0932771,"remaining_time":256.8712343},
{"learn":[0.370340017],"iteration":753,"passed_time":784.9977737,"remaining_time":256.113332},
{"learn":[0.3702912592],"iteration":754,"passed_time":786.3020759,"remaining_time":255.1576273},
{"learn":[0.3702314052],"iteration":755,"passed_time":787.5331847,"remaining_time":254.1773771},
{"learn":[0.3701817749],"iteration":756,"passed_time":788.6407068,"remaining_time":253.1567923},
{"learn":[0.3701418262],"iteration":757,"passed_time":789.5445501,"remaining_time":252.0709513},
{"learn":[0.3700829538],"iteration":758,"passed_time":790.6698693,"remaining_time":251.0559137},
{"learn":[0.3700276344],"iteration":759,"passed_time":791.7046448,"remaining_time":250.0119931},
{"learn":[0.369971086],"iteration":760,"passed_time":792.9313247,"remaining_time":249.0283661},
{"learn":[0.3699122356],"iteration":761,"passed_time":794.4670055,"remaining_time":248.1406133},
{"learn":[0.3698609059],"iteration":762,"passed_time":796.0111948,"remaining_time":247.253805},
{"learn":[0.3698047246],"iteration":763,"passed_time":797.5027525,"remaining_time":246.3490178},
{"learn":[0.369727566],"iteration":764,"passed_time":798.7696466,"remaining_time":245.3736823},
{"learn":[0.3696685566],"iteration":765,"passed_time":800.2109304,"remaining_time":244.4508586},
{"learn":[0.369601087],"iteration":766,"passed_time":801.5853326,"remaining_time":243.5063657},
{"learn":[0.3695511736],"iteration":767,"passed_time":802.6725237,"remaining_time":242.4739915},
{"learn":[0.3694914171],"iteration":768,"passed_time":803.9895284,"remaining_time":241.5105085},
{"learn":[0.3694394541],"iteration":769,"passed_time":805.3021233,"remaining_time":240.5447901},
{"learn":[0.3693766963],"iteration":770,"passed_time":806.5489184,"remaining_time":239.5586282},
{"learn":[0.3693235524],"iteration":771,"passed_time":807.6451676,"remaining_time":238.5273293},
{"learn":[0.3692584312],"iteration":772,"passed_time":809.1881048,"remaining_time":237.6270373},
{"learn":[0.3691900724],"iteration":773,"passed_time":810.6870111,"remaining_time":236.7122281},
{"learn":[0.3690381263],"iteration":774,"passed_time":812.2069685,"remaining_time":235.8020231},
{"learn":[0.3689791938],"iteration":775,"passed_time":813.3538209,"remaining_time":234.7825462},
{"learn":[0.36893286],"iteration":776,"passed_time":814.3218083,"remaining_time":233.711407},
{"learn":[0.3688687865],"iteration":777,"passed_time":815.6828641,"remaining_time":232.7526939},
{"learn":[0.3688111583],"iteration":778,"passed_time":816.8243597,"remaining_time":231.7306592},
{"learn":[0.3687507884],"iteration":779,"passed_time":818.1599827,"remaining_time":230.763072},
{"learn":[0.3686947755],"iteration":780,"passed_time":819.5580442,"remaining_time":229.8120508},
{"learn":[0.3686367522],"iteration":781,"passed_time":820.86162,"remaining_time":228.8335462},
{"learn":[0.3685755992],"iteration":782,"passed_time":822.3560804,"remaining_time":227.907113},
{"learn":[0.36852846],"iteration":783,"passed_time":823.4354341,"remaining_time":226.8648645},
{"learn":[0.3684809195],"iteration":784,"passed_time":824.4665897,"remaining_time":225.8093207},
{"learn":[0.3684140186],"iteration":785,"passed_time":825.9528923,"remaining_time":224.8777595},
{"learn":[0.3683608759],"iteration":786,"passed_time":827.1595177,"remaining_time":223.8690944},
{"learn":[0.3683055267],"iteration":787,"passed_time":828.5716059,"remaining_time":222.9152036},
{"learn":[0.3682439799],"iteration":788,"passed_time":830.6685234,"remaining_time":222.1432933},
{"learn":[0.3681872323],"iteration":789,"passed_time":832.0744011,"remaining_time":221.1843345},
{"learn":[0.3681427727],"iteration":790,"passed_time":833.1362349,"remaining_time":220.1333414},
{"learn":[0.368092071],"iteration":791,"passed_time":834.0025726,"remaining_time":219.0309787},
{"learn":[0.3680282624],"iteration":792,"passed_time":835.215316,"remaining_time":218.0196348},
{"learn":[0.3679682053],"iteration":793,"passed_time":836.3331508,"remaining_time":216.98316},
{"learn":[0.3679099658],"iteration":794,"passed_time":837.4344614,"remaining_time":215.9422196},
{"learn":[0.3678606879],"iteration":795,"passed_time":838.4324135,"remaining_time":214.8746386},
{"learn":[0.367803262],"iteration":796,"passed_time":839.9145534,"remaining_time":213.9305575},
{"learn":[0.3677089519],"iteration":797,"passed_time":841.3569117,"remaining_time":212.9750578},
{"learn":[0.367657678],"iteration":798,"passed_time":842.3957005,"remaining_time":211.9168158},
{"learn":[0.3675997735],"iteration":799,"passed_time":843.9008747,"remaining_time":210.9752187},
{"learn":[0.3675447387],"iteration":800,"passed_time":845.7982105,"remaining_time":210.1296428},
{"learn":[0.367492656],"iteration":801,"passed_time":847.0528708,"remaining_time":209.1227786},
{"learn":[0.3674360312],"iteration":802,"passed_time":848.0617666,"remaining_time":208.0550038},
{"learn":[0.3673733398],"iteration":803,"passed_time":849.4358482,"remaining_time":207.0764008},
{"learn":[0.3673211688],"iteration":804,"passed_time":850.4830648,"remaining_time":206.0176368},
{"learn":[0.3672587079],"iteration":805,"passed_time":851.6977273,"remaining_time":204.9992048},
{"learn":[0.3672025503],"iteration":806,"passed_time":852.6980868,"remaining_time":203.9290344},
{"learn":[0.3671563831],"iteration":807,"passed_time":853.8300941,"remaining_time":202.8903194},
{"learn":[0.3670977266],"iteration":808,"passed_time":855.1174857,"remaining_time":201.888059},
{"learn":[0.3670425763],"iteration":809,"passed_time":856.2389818,"remaining_time":200.8461809},
{"learn":[0.3669856136],"iteration":810,"passed_time":857.4231829,"remaining_time":199.8187196},
{"learn":[0.3669249583],"iteration":811,"passed_time":858.9746059,"remaining_time":198.875894},
{"learn":[0.3668680662],"iteration":812,"passed_time":860.3712293,"remaining_time":197.8959654},
{"learn":[0.3668041885],"iteration":813,"passed_time":861.8771276,"remaining_time":196.9399825},
{"learn":[0.3667582943],"iteration":814,"passed_time":862.9849372,"remaining_time":195.8922864},
{"learn":[0.3667010507],"iteration":815,"passed_time":864.5182352,"remaining_time":194.9403864},
{"learn":[0.3666466699],"iteration":816,"passed_time":866.2665216,"remaining_time":194.0352184},
{"learn":[0.3665908755],"iteration":817,"passed_time":867.5950479,"remaining_time":193.034595},
{"learn":[0.3665357084],"iteration":818,"passed_time":868.6754257,"remaining_time":191.9783297},
{"learn":[0.3664775631],"iteration":819,"passed_time":869.9304029,"remaining_time":190.9603323},
{"learn":[0.3664247247],"iteration":820,"passed_time":871.2552295,"remaining_time":189.9569867},
{"learn":[0.366369201],"iteration":821,"passed_time":872.3569505,"remaining_time":188.9045465},
{"learn":[0.3663222596],"iteration":822,"passed_time":873.2281395,"remaining_time":187.8024067},
{"learn":[0.3662636777],"iteration":823,"passed_time":874.7057082,"remaining_time":186.8303454},
{"learn":[0.3662095268],"iteration":824,"passed_time":876.0082504,"remaining_time":185.8199319},
{"learn":[0.3661506087],"iteration":825,"passed_time":877.8027698,"remaining_time":184.9124479},
{"learn":[0.3660841079],"iteration":826,"passed_time":879.2483145,"remaining_time":183.9298167},
{"learn":[0.3660219431],"iteration":827,"passed_time":880.4346551,"remaining_time":182.892223},
{"learn":[0.3659614176],"iteration":828,"passed_time":881.6318174,"remaining_time":181.8565028},
{"learn":[0.3659006053],"iteration":829,"passed_time":883.0023703,"remaining_time":180.8559072},
{"learn":[0.3658374621],"iteration":830,"passed_time":884.5066904,"remaining_time":179.8816254},
{"learn":[0.3657878188],"iteration":831,"passed_time":886.1670823,"remaining_time":178.9375839},
{"learn":[0.3657346637],"iteration":832,"passed_time":887.3828251,"remaining_time":177.9026792},
{"learn":[0.3656793654],"iteration":833,"passed_time":888.3479197,"remaining_time":176.8174516},
{"learn":[0.3656341939],"iteration":834,"passed_time":889.1936143,"remaining_time":175.7089178},
{"learn":[0.3655759748],"iteration":835,"passed_time":890.3895215,"remaining_time":174.6697147},
{"learn":[0.3655055627],"iteration":836,"passed_time":891.9276288,"remaining_time":173.6967784},
{"learn":[0.3654455175],"iteration":837,"passed_time":893.2138474,"remaining_time":172.6737987},
{"learn":[0.3653801648],"iteration":838,"passed_time":895.1057053,"remaining_time":171.7664107},
{"learn":[0.365319586],"iteration":839,"passed_time":896.5525514,"remaining_time":170.7719146},
{"learn":[0.3652622219],"iteration":840,"passed_time":897.6837768,"remaining_time":169.7166712},
{"learn":[0.3652118245],"iteration":841,"passed_time":898.9183991,"remaining_time":168.6806497},
{"learn":[0.3651499258],"iteration":842,"passed_time":900.0017515,"remaining_time":167.6159846},
{"learn":[0.3651002279],"iteration":843,"passed_time":901.0801631,"remaining_time":166.5503619},
{"learn":[0.3650383335],"iteration":844,"passed_time":902.6180878,"remaining_time":165.5689983},
{"learn":[0.3649659827],"iteration":845,"passed_time":904.7418688,"remaining_time":164.6929643},
{"learn":[0.3649148387],"iteration":846,"passed_time":905.8282422,"remaining_time":163.6265892},
{"learn":[0.3648797394],"iteration":847,"passed_time":906.8697057,"remaining_time":162.5521171},
{"learn":[0.3648333071],"iteration":848,"passed_time":908.1099999,"remaining_time":161.513086},
{"learn":[0.3647812047],"iteration":849,"passed_time":909.2250511,"remaining_time":160.4514796},
{"learn":[0.3647206014],"iteration":850,"passed_time":910.3045242,"remaining_time":159.3835183},
{"learn":[0.3646523822],"iteration":851,"passed_time":911.7926564,"remaining_time":158.3865178},
{"learn":[0.364594001],"iteration":852,"passed_time":913.2076501,"remaining_time":157.3757615},
{"learn":[0.3645333289],"iteration":853,"passed_time":914.8268257,"remaining_time":156.3989655},
{"learn":[0.3644682603],"iteration":854,"passed_time":915.8933051,"remaining_time":155.3269348},
{"learn":[0.3644130148],"iteration":855,"passed_time":917.0555989,"remaining_time":154.2710353},
{"learn":[0.3643440443],"iteration":856,"passed_time":918.4151797,"remaining_time":153.2478071},
{"learn":[0.3642859965],"iteration":857,"passed_time":920.0694496,"remaining_time":152.2725663},
{"learn":[0.364223763],"iteration":858,"passed_time":921.1428186,"remaining_time":151.2003928},
{"learn":[0.3641640603],"iteration":859,"passed_time":922.3302492,"remaining_time":150.1467847},
{"learn":[0.3641251392],"iteration":860,"passed_time":923.275824,"remaining_time":149.0538206},
{"learn":[0.3640746902],"iteration":861,"passed_time":924.5216781,"remaining_time":148.009271},
{"learn":[0.3640180667],"iteration":862,"passed_time":926.4493844,"remaining_time":147.0724979},
{"learn":[0.3639671166],"iteration":863,"passed_time":928.0355088,"remaining_time":146.0796634},
{"learn":[0.3639157766],"iteration":864,"passed_time":929.0518016,"remaining_time":144.996524},
{"learn":[0.3638605031],"iteration":865,"passed_time":930.3378184,"remaining_time":143.9552744},
{"learn":[0.3638094247],"iteration":866,"passed_time":931.2303869,"remaining_time":142.8531043},
{"learn":[0.3637588284],"iteration":867,"passed_time":932.4010193,"remaining_time":141.7937034},
{"learn":[0.3637049339],"iteration":868,"passed_time":933.7965533,"remaining_time":140.7679499},
{"learn":[0.3636451729],"iteration":869,"passed_time":935.5765102,"remaining_time":139.7987889},
{"learn":[0.3635900125],"iteration":870,"passed_time":937.0218204,"remaining_time":138.778203},
{"learn":[0.3635321651],"iteration":871,"passed_time":938.2202596,"remaining_time":137.7204051},
{"learn":[0.363474966],"iteration":872,"passed_time":939.4281998,"remaining_time":136.6636671},
{"learn":[0.3634250219],"iteration":873,"passed_time":940.4268126,"remaining_time":135.5764055},
{"learn":[0.3633727143],"iteration":874,"passed_time":941.2651501,"remaining_time":134.46645},
{"learn":[0.3633120437],"iteration":875,"passed_time":942.4772301,"remaining_time":133.4100189},
{"learn":[0.3632537453],"iteration":876,"passed_time":943.7087574,"remaining_time":132.3559603},
{"learn":[0.3632040706],"iteration":877,"passed_time":945.1949293,"remaining_time":131.3368808},
{"learn":[0.3631427402],"iteration":878,"passed_time":946.7430659,"remaining_time":130.3252685},
{"learn":[0.3630971722],"iteration":879,"passed_time":947.8409728,"remaining_time":129.2510417},
{"learn":[0.3630357279],"iteration":880,"passed_time":949.0851767,"remaining_time":128.1965222},
{"learn":[0.3629787002],"iteration":881,"passed_time":950.3458095,"remaining_time":127.1437704},
{"learn":[0.3629245487],"iteration":882,"passed_time":951.372041,"remaining_time":126.059489},
{"learn":[0.3628558664],"iteration":883,"passed_time":952.7235606,"remaining_time":125.0180238},
{"learn":[0.3628262716],"iteration":884,"passed_time":953.5754175,"remaining_time":123.91093},
{"learn":[0.3627690546],"iteration":885,"passed_time":955.2769649,"remaining_time":122.9137404},
{"learn":[0.3627181149],"iteration":886,"passed_time":956.8551973,"remaining_time":121.8992529},
{"learn":[0.3626592037],"iteration":887,"passed_time":958.3961024,"remaining_time":120.8787877},
{"learn":[0.3625955905],"iteration":888,"passed_time":959.7277708,"remaining_time":119.8310265},
{"learn":[0.3625400139],"iteration":889,"passed_time":960.7788744,"remaining_time":118.7479508},
{"learn":[0.362497645],"iteration":890,"passed_time":961.5705914,"remaining_time":117.6332149},
{"learn":[0.3624349396],"iteration":891,"passed_time":962.5559217,"remaining_time":116.5426452},
{"learn":[0.3623795574],"iteration":892,"passed_time":963.7581432,"remaining_time":115.4782994},
{"learn":[0.3623121466],"iteration":893,"passed_time":965.4040057,"remaining_time":114.4662468},
{"learn":[0.3622569619],"iteration":894,"passed_time":966.5772814,"remaining_time":113.3973347},
{"learn":[0.3622097577],"iteration":895,"passed_time":967.6873617,"remaining_time":112.3208545},
{"learn":[0.3621511055],"iteration":896,"passed_time":969.1111147,"remaining_time":111.2803175},
{"learn":[0.3621048686],"iteration":897,"passed_time":970.7814392,"remaining_time":110.2669341},
{"learn":[0.3620722371],"iteration":898,"passed_time":972.0875925,"remaining_time":109.2111756},
{"learn":[0.3620129458],"iteration":899,"passed_time":973.4013844,"remaining_time":108.1557094},
{"learn":[0.3619656472],"iteration":900,"passed_time":974.5916152,"remaining_time":107.0860931},
{"learn":[0.3619148144],"iteration":901,"passed_time":975.6354997,"remaining_time":106.0003093},
{"learn":[0.3618631535],"iteration":902,"passed_time":976.6860297,"remaining_time":104.9153321},
{"learn":[0.3617990745],"iteration":903,"passed_time":977.7491532,"remaining_time":103.8317685},
{"learn":[0.3617485899],"iteration":904,"passed_time":979.085994,"remaining_time":102.7769828},
{"learn":[0.3616901883],"iteration":905,"passed_time":980.3956771,"remaining_time":101.7187568},
{"learn":[0.361642976],"iteration":906,"passed_time":981.4886557,"remaining_time":100.6377563},
{"learn":[0.3615910807],"iteration":907,"passed_time":982.6267717,"remaining_time":99.56130286},
{"learn":[0.3615333232],"iteration":908,"passed_time":983.9700112,"remaining_time":98.50524865},
{"learn":[0.361445401],"iteration":909,"passed_time":985.7274516,"remaining_time":97.48952818},
{"learn":[0.3613935352],"iteration":910,"passed_time":987.3404023,"remaining_time":96.45806345},
{"learn":[0.3613336208],"iteration":911,"passed_time":989.0651464,"remaining_time":95.43611062},
{"learn":[0.361272667],"iteration":912,"passed_time":989.9844448,"remaining_time":94.33586714},
{"learn":[0.3612207039],"iteration":913,"passed_time":991.035751,"remaining_time":93.24844047},
{"learn":[0.3611526009],"iteration":914,"passed_time":992.1663579,"remaining_time":92.16845948},
{"learn":[0.361113993],"iteration":915,"passed_time":993.0687546,"remaining_time":91.06744038},
{"learn":[0.3610426949],"iteration":916,"passed_time":994.6330037,"remaining_time":90.02676042},
{"learn":[0.3610005423],"iteration":917,"passed_time":995.7590911,"remaining_time":88.94580116},
{"learn":[0.3609415554],"iteration":918,"passed_time":997.1640169,"remaining_time":87.88932031},
{"learn":[0.3608788527],"iteration":919,"passed_time":998.9499879,"remaining_time":86.86521634},
{"learn":[0.3608232251],"iteration":920,"passed_time":1000.363151,"remaining_time":85.80747987},
{"learn":[0.360786669],"iteration":921,"passed_time":1001.551799,"remaining_time":84.72997863},
{"learn":[0.3607293014],"iteration":922,"passed_time":1002.663021,"remaining_time":83.6457775},
{"learn":[0.3606882273],"iteration":923,"passed_time":1003.587234,"remaining_time":82.54613614},
{"learn":[0.3606289093],"iteration":924,"passed_time":1004.832179,"remaining_time":81.47287938},
{"learn":[0.360585386],"iteration":925,"passed_time":1005.767966,"remaining_time":80.3745459},
{"learn":[0.3605244216],"iteration":926,"passed_time":1006.830656,"remaining_time":79.28655655},
{"learn":[0.3604617289],"iteration":927,"passed_time":1008.364792,"remaining_time":78.23519938},
{"learn":[0.3604051563],"iteration":928,"passed_time":1009.991781,"remaining_time":77.18989929},
{"learn":[0.3603487935],"iteration":929,"passed_time":1011.53837,"remaining_time":76.13729665},
{"learn":[0.3603023499],"iteration":930,"passed_time":1012.601836,"remaining_time":75.04782676},
{"learn":[0.3602432276],"iteration":931,"passed_time":1013.781381,"remaining_time":73.96688187},
{"learn":[0.3601802409],"iteration":932,"passed_time":1015.024017,"remaining_time":72.89025631},
{"learn":[0.360117157],"iteration":933,"passed_time":1016.125945,"remaining_time":71.80333229},
{"learn":[0.3600677343],"iteration":934,"passed_time":1017.054583,"remaining_time":70.70432932},
{"learn":[0.3600036682],"iteration":935,"passed_time":1018.372774,"remaining_time":69.63232641},
{"learn":[0.3599550134],"iteration":936,"passed_time":1019.803885,"remaining_time":68.56739036},
{"learn":[0.3599042307],"iteration":937,"passed_time":1021.126397,"remaining_time":67.49449531},
{"learn":[0.359843858],"iteration":938,"passed_time":1022.330457,"remaining_time":66.4133737},
{"learn":[0.3597565074],"iteration":939,"passed_time":1024.143438,"remaining_time":65.37085775},
{"learn":[0.3597043872],"iteration":940,"passed_time":1025.704896,"remaining_time":64.31093398},
{"learn":[0.3596444962],"iteration":941,"passed_time":1027.23023,"remaining_time":63.2477212},
{"learn":[0.3595884039],"iteration":942,"passed_time":1028.597503,"remaining_time":62.17397417},
{"learn":[0.3595279634],"iteration":943,"passed_time":1029.848229,"remaining_time":61.09269157},
{"learn":[0.3594795368],"iteration":944,"passed_time":1030.851335,"remaining_time":59.99663856},
{"learn":[0.3594192847],"iteration":945,"passed_time":1031.937281,"remaining_time":58.90551074},
{"learn":[0.3593596441],"iteration":946,"passed_time":1033.095737,"remaining_time":57.81845202},
{"learn":[0.3593148324],"iteration":947,"passed_time":1034.073659,"remaining_time":56.72133992},
{"learn":[0.359253704],"iteration":948,"passed_time":1035.749839,"remaining_time":55.66200398},
{"learn":[0.3592057923],"iteration":949,"passed_time":1036.908194,"remaining_time":54.57411547},
{"learn":[0.3591454497],"iteration":950,"passed_time":1038.115189,"remaining_time":53.48858494},
{"learn":[0.359085053],"iteration":951,"passed_time":1040.059246,"remaining_time":52.43996197},
{"learn":[0.3590324741],"iteration":952,"passed_time":1041.524927,"remaining_time":51.36586732},
{"learn":[0.3589881369],"iteration":953,"passed_time":1042.925497,"remaining_time":50.28781221},
{"learn":[0.3589287931],"iteration":954,"passed_time":1044.448287,"remaining_time":49.21484074},
{"learn":[0.3588810228],"iteration":955,"passed_time":1045.705868,"remaining_time":48.12872196},
{"learn":[0.3588318775],"iteration":956,"passed_time":1046.912114,"remaining_time":47.03993826},
{"learn":[0.3587693597],"iteration":957,"passed_time":1048.312053,"remaining_time":45.95940105},
{"learn":[0.3587156802],"iteration":958,"passed_time":1049.903457,"remaining_time":44.88638346},
{"learn":[0.3586533131],"iteration":959,"passed_time":1051.803561,"remaining_time":43.82514836},
{"learn":[0.3585910867],"iteration":960,"passed_time":1053.56838,"remaining_time":42.75667721},
{"learn":[0.3585396371],"iteration":961,"passed_time":1054.618744,"remaining_time":41.65853666},
{"learn":[0.3584868476],"iteration":962,"passed_time":1055.719819,"remaining_time":40.56244373},
{"learn":[0.358443332],"iteration":963,"passed_time":1056.876943,"remaining_time":39.46843356},
{"learn":[0.3583882417],"iteration":964,"passed_time":1058.218457,"remaining_time":38.3809803},
{"learn":[0.3583423469],"iteration":965,"passed_time":1059.758662,"remaining_time":37.2999943},
{"learn":[0.358311248],"iteration":966,"passed_time":1060.851238,"remaining_time":36.2027827},
{"learn":[0.3582566768],"iteration":967,"passed_time":1062.440347,"remaining_time":35.12199495},
{"learn":[0.3582053116],"iteration":968,"passed_time":1063.750971,"remaining_time":34.03124883},
{"learn":[0.3581556933],"iteration":969,"passed_time":1064.984866,"remaining_time":32.93767626},
{"learn":[0.3580918212],"iteration":970,"passed_time":1066.481667,"remaining_time":31.85166666},
{"learn":[0.3580323043],"iteration":971,"passed_time":1067.898465,"remaining_time":30.76250722},
{"learn":[0.357971368],"iteration":972,"passed_time":1068.986665,"remaining_time":29.66355597},
{"learn":[0.3579144348],"iteration":973,"passed_time":1070.312564,"remaining_time":28.57097195},
{"learn":[0.357859872],"iteration":974,"passed_time":1071.884075,"remaining_time":27.48420706},
{"learn":[0.3578068184],"iteration":975,"passed_time":1073.147689,"remaining_time":26.38887759},
{"learn":[0.3577578126],"iteration":976,"passed_time":1074.131852,"remaining_time":25.28662497},
{"learn":[0.357699914],"iteration":977,"passed_time":1075.740074,"remaining_time":24.19865197},
{"learn":[0.357658323],"iteration":978,"passed_time":1076.942099,"remaining_time":23.10090305},
{"learn":[0.3575953748],"iteration":979,"passed_time":1078.501066,"remaining_time":22.01022584},
{"learn":[0.3575387068],"iteration":980,"passed_time":1079.747204,"remaining_time":20.91253505},
{"learn":[0.3574821125],"iteration":981,"passed_time":1081.30439,"remaining_time":19.8202434},
{"learn":[0.3574381097],"iteration":982,"passed_time":1082.293596,"remaining_time":18.71718324},
{"learn":[0.3573830162],"iteration":983,"passed_time":1083.594755,"remaining_time":17.6194269},
{"learn":[0.3573251251],"iteration":984,"passed_time":1084.696197,"remaining_time":16.51821619},
{"learn":[0.3572761102],"iteration":985,"passed_time":1085.905231,"remaining_time":15.41853269},
{"learn":[0.3572088697],"iteration":986,"passed_time":1087.488886,"remaining_time":14.32356182},
{"learn":[0.3571394878],"iteration":987,"passed_time":1088.819786,"remaining_time":13.22453182},
{"learn":[0.357078208],"iteration":988,"passed_time":1090.410631,"remaining_time":12.12792411},
{"learn":[0.3570196631],"iteration":989,"passed_time":1091.679851,"remaining_time":11.02706921},
{"learn":[0.3569725897],"iteration":990,"passed_time":1092.700141,"remaining_time":9.923613793},
{"learn":[0.356914776],"iteration":991,"passed_time":1094.016373,"remaining_time":8.822712682},
{"learn":[0.3568535489],"iteration":992,"passed_time":1095.232573,"remaining_time":7.720672724},
{"learn":[0.3567995838],"iteration":993,"passed_time":1096.564504,"remaining_time":6.619101636},
{"learn":[0.356759166],"iteration":994,"passed_time":1097.96049,"remaining_time":5.517389399},
{"learn":[0.3567116476],"iteration":995,"passed_time":1099.509378,"remaining_time":4.415700314},
{"learn":[0.3566590112],"iteration":996,"passed_time":1101.29907,"remaining_time":3.313838727},
{"learn":[0.3566056674],"iteration":997,"passed_time":1102.557195,"remaining_time":2.209533458},
{"learn":[0.3565541339],"iteration":998,"passed_time":1103.818032,"remaining_time":1.104922955},
{"learn":[0.3564944102],"iteration":999,"passed_time":1105.356744,"remaining_time":0}
]}